{"date": "2014-05-17", "tracks": [{"id": 16, "name": "G\u00e4vle", "startTime": "2014-05-17T12:45:00", "races": [{"id": "2014-05-17_16_1", "number": 1, "status": "results", "startTime": "2014-05-17T12:45:13"}, {"id": "2014-05-17_16_2", "number": 2, "status": "results", "startTime": "2014-05-17T13:05:12"}, {"id": "2014-05-17_16_3", "number": 3, "status": "results", "startTime": "2014-05-17T13:26:53"}, {"id": "2014-05-17_16_4", "number": 4, "status": "results", "startTime": "2014-05-17T13:46:55"}, {"id": "2014-05-17_16_5", "number": 5, "status": "results", "startTime": "2014-05-17T14:30:35"}, {"id": "2014-05-17_16_6", "number": 6, "status": "results", "startTime": "2014-05-17T14:56:25"}, {"id": "2014-05-17_16_7", "number": 7, "status": "results", "startTime": "2014-05-17T15:16:41"}, {"id": "2014-05-17_16_8", "number": 8, "status": "results", "startTime": "2014-05-17T15:37:33"}, {"id": "2014-05-17_16_9", "number": 9, "status": "results", "startTime": "2014-05-17T15:59:13"}, {"id": "2014-05-17_16_10", "number": 10, "status": "results", "startTime": "2014-05-17T16:25:51"}, {"id": "2014-05-17_16_11", "number": 11, "status": "results", "startTime": "2014-05-17T16:48:44"}, {"id": "2014-05-17_16_12", "number": 12, "status": "results", "startTime": "2014-05-17T17:07:57"}, {"id": "2014-05-17_16_13", "number": 13, "status": "results", "startTime": "2014-05-17T17:25:25"}], "sport": "trot", "biggestGameType": "V75"}, {"id": 29, "name": "\u00c5m\u00e5l", "startTime": "2014-05-17T17:35:00", "races": [{"id": "2014-05-17_29_1", "number": 1, "status": "results", "startTime": "2014-05-17T17:36:50"}, {"id": "2014-05-17_29_2", "number": 2, "status": "results", "startTime": "2014-05-17T17:57:05"}, {"id": "2014-05-17_29_3", "number": 3, "status": "results", "startTime": "2014-05-17T18:25:58"}, {"id": "2014-05-17_29_4", "number": 4, "status": "results", "startTime": "2014-05-17T18:46:29"}, {"id": "2014-05-17_29_5", "number": 5, "status": "results", "startTime": "2014-05-17T19:06:20"}, {"id": "2014-05-17_29_6", "number": 6, "status": "results", "startTime": "2014-05-17T19:26:17"}, {"id": "2014-05-17_29_7", "number": 7, "status": "results", "startTime": "2014-05-17T19:46:36"}, {"id": "2014-05-17_29_8", "number": 8, "status": "results", "startTime": "2014-05-17T20:07:04"}, {"id": "2014-05-17_29_9", "number": 9, "status": "results", "startTime": "2014-05-17T20:25:55"}, {"id": "2014-05-17_29_10", "number": 10, "status": "results", "startTime": "2014-05-17T20:51:18"}], "sport": "trot", "biggestGameType": "V65"}, {"id": 79, "name": "\u00d6vrevoll", "startTime": "2014-05-17T15:25:00", "races": [{"id": "2014-05-17_79_1", "number": 1, "status": "results", "startTime": "2014-05-17T15:25:00"}, {"id": "2014-05-17_79_2", "number": 2, "status": "results", "startTime": "2014-05-17T15:50:00"}, {"id": "2014-05-17_79_3", "number": 3, "status": "results", "startTime": "2014-05-17T16:12:00"}, {"id": "2014-05-17_79_4", "number": 4, "status": "results", "startTime": "2014-05-17T16:34:00"}, {"id": "2014-05-17_79_5", "number": 5, "status": "results", "startTime": "2014-05-17T17:00:00"}, {"id": "2014-05-17_79_6", "number": 6, "status": "results", "startTime": "2014-05-17T17:22:00"}, {"id": "2014-05-17_79_7", "number": 7, "status": "results", "startTime": "2014-05-17T17:46:00"}, {"id": "2014-05-17_79_8", "number": 8, "status": "results", "startTime": "2014-05-17T18:10:00"}, {"id": "2014-05-17_79_9", "number": 9, "status": "results", "startTime": "2014-05-17T18:35:00"}, {"id": "2014-05-17_79_10", "number": 10, "status": "results", "startTime": "2014-05-17T18:55:00"}], "sport": "gallop", "biggestGameType": "V5"}], "games": {"V75": [{"id": "V75_2014-05-17_16_5", "status": "results", "startTime": "2014-05-17T14:30:35", "scheduledStartTime": "2014-05-17T14:30:00", "tracks": [16], "races": ["2014-05-17_16_5", "2014-05-17_16_6", "2014-05-17_16_7", "2014-05-17_16_8", "2014-05-17_16_9", "2014-05-17_16_10", "2014-05-17_16_11"]}], "V65": [{"id": "V65_2014-05-17_29_3", "status": "results", "startTime": "2014-05-17T18:25:58", "scheduledStartTime": "2014-05-17T18:25:00", "tracks": [29], "jackpotAmount": 442427, "races": ["2014-05-17_29_3", "2014-05-17_29_4", "2014-05-17_29_5", "2014-05-17_29_6", "2014-05-17_29_7", "2014-05-17_29_8"]}], "V5": [{"id": "V5_2014-05-17_16_7", "status": "results", "startTime": "2014-05-17T15:16:41", "scheduledStartTime": "2014-05-17T15:15:00", "tracks": [16], "races": ["2014-05-17_16_7", "2014-05-17_16_8", "2014-05-17_16_9", "2014-05-17_16_10", "2014-05-17_16_11"]}, {"id": "V5_2014-05-17_79_5", "status": "results", "startTime": "2014-05-17T17:00:00", "scheduledStartTime": "2014-05-17T17:00:00", "tracks": [79], "races": ["2014-05-17_79_5", "2014-05-17_79_6", "2014-05-17_79_7", "2014-05-17_79_8", "2014-05-17_79_9"]}], "V4": [{"id": "V4_2014-05-17_16_1", "status": "results", "startTime": "2014-05-17T12:45:13", "scheduledStartTime": "2014-05-17T12:45:00", "tracks": [16], "races": ["2014-05-17_16_1", "2014-05-17_16_2", "2014-05-17_16_3", "2014-05-17_16_4"]}, {"id": "V4_2014-05-17_29_5", "status": "results", "startTime": "2014-05-17T19:06:20", "scheduledStartTime": "2014-05-17T19:05:00", "tracks": [29], "races": ["2014-05-17_29_5", "2014-05-17_29_6", "2014-05-17_29_7", "2014-05-17_29_8"]}], "V3": [{"id": "V3_2014-05-17_16_11", "status": "results", "startTime": "2014-05-17T16:48:44", "scheduledStartTime": "2014-05-17T16:48:00", "tracks": [16], "races": ["2014-05-17_16_11", "2014-05-17_16_12", "2014-05-17_16_13"]}, {"id": "V3_2014-05-17_29_8", "status": "results", "startTime": "2014-05-17T20:07:04", "scheduledStartTime": "2014-05-17T20:05:00", "tracks": [29], "races": ["2014-05-17_29_8", "2014-05-17_29_9", "2014-05-17_29_10"]}], "dd": [{"id": "dd_2014-05-17_16_10", "status": "results", "startTime": "2014-05-17T16:25:51", "scheduledStartTime": "2014-05-17T16:25:00", "tracks": [16], "races": ["2014-05-17_16_10", "2014-05-17_16_11"]}], "ld": [{"id": "ld_2014-05-17_16_2", "status": "results", "startTime": "2014-05-17T13:05:12", "scheduledStartTime": "2014-05-17T13:05:00", "tracks": [16], "races": ["2014-05-17_16_2", "2014-05-17_16_3"]}], "trio": [{"id": "trio_2014-05-17_16_4", "status": "results", "startTime": "2014-05-17T13:46:55", "scheduledStartTime": "2014-05-17T13:45:00", "tracks": [16], "races": ["2014-05-17_16_4"]}, {"id": "trio_2014-05-17_16_9", "status": "results", "startTime": "2014-05-17T15:59:13", "scheduledStartTime": "2014-05-17T15:59:00", "tracks": [16], "races": ["2014-05-17_16_9"]}, {"id": "trio_2014-05-17_16_13", "status": "results", "startTime": "2014-05-17T17:25:25", "scheduledStartTime": "2014-05-17T17:25:00", "tracks": [16], "races": ["2014-05-17_16_13"]}, {"id": "trio_2014-05-17_29_6", "status": "results", "startTime": "2014-05-17T19:26:17", "scheduledStartTime": "2014-05-17T19:25:00", "tracks": [29], "races": ["2014-05-17_29_6"]}, {"id": "trio_2014-05-17_29_10", "status": "results", "startTime": "2014-05-17T20:51:18", "scheduledStartTime": "2014-05-17T20:45:00", "tracks": [29], "races": ["2014-05-17_29_10"]}, {"id": "trio_2014-05-17_79_1", "status": "results", "startTime": "2014-05-17T15:25:00", "scheduledStartTime": "2014-05-17T15:25:00", "tracks": [79], "races": ["2014-05-17_79_1"]}, {"id": "trio_2014-05-17_79_2", "status": "results", "startTime": "2014-05-17T15:50:00", "scheduledStartTime": "2014-05-17T15:50:00", "tracks": [79], "races": ["2014-05-17_79_2"]}, {"id": "trio_2014-05-17_79_3", "status": "results", "startTime": "2014-05-17T16:12:00", "scheduledStartTime": "2014-05-17T16:12:00", "tracks": [79], "races": ["2014-05-17_79_3"]}, {"id": "trio_2014-05-17_79_4", "status": "results", "startTime": "2014-05-17T16:34:00", "scheduledStartTime": "2014-05-17T16:34:00", "tracks": [79], "races": ["2014-05-17_79_4"]}, {"id": "trio_2014-05-17_79_5", "status": "results", "startTime": "2014-05-17T17:00:00", "scheduledStartTime": "2014-05-17T17:00:00", "tracks": [79], "races": ["2014-05-17_79_5"]}, {"id": "trio_2014-05-17_79_6", "status": "results", "startTime": "2014-05-17T17:22:00", "scheduledStartTime": "2014-05-17T17:22:00", "tracks": [79], "races": ["2014-05-17_79_6"]}, {"id": "trio_2014-05-17_79_7", "status": "results", "startTime": "2014-05-17T17:46:00", "scheduledStartTime": "2014-05-17T17:46:00", "tracks": [79], "races": ["2014-05-17_79_7"]}, {"id": "trio_2014-05-17_79_8", "status": "results", "startTime": "2014-05-17T18:10:00", "scheduledStartTime": "2014-05-17T18:10:00", "tracks": [79], "races": ["2014-05-17_79_8"]}, {"id": "trio_2014-05-17_79_9", "status": "results", "startTime": "2014-05-17T18:35:00", "scheduledStartTime": "2014-05-17T18:35:00", "tracks": [79], "races": ["2014-05-17_79_9"]}, {"id": "trio_2014-05-17_79_10", "status": "results", "startTime": "2014-05-17T18:55:00", "scheduledStartTime": "2014-05-17T18:55:00", "tracks": [79], "races": ["2014-05-17_79_10"]}], "komb": [{"id": "komb_2014-05-17_79_1", "status": "results", "startTime": "2014-05-17T15:25:00", "scheduledStartTime": "2014-05-17T15:25:00", "tracks": [79], "races": ["2014-05-17_79_1"]}, {"id": "komb_2014-05-17_79_2", "status": "results", "startTime": "2014-05-17T15:50:00", "scheduledStartTime": "2014-05-17T15:50:00", "tracks": [79], "races": ["2014-05-17_79_2"]}, {"id": "komb_2014-05-17_79_3", "status": "results", "startTime": "2014-05-17T16:12:00", "scheduledStartTime": "2014-05-17T16:12:00", "tracks": [79], "races": ["2014-05-17_79_3"]}, {"id": "komb_2014-05-17_79_4", "status": "results", "startTime": "2014-05-17T16:34:00", "scheduledStartTime": "2014-05-17T16:34:00", "tracks": [79], "races": ["2014-05-17_79_4"]}, {"id": "komb_2014-05-17_79_5", "status": "results", "startTime": "2014-05-17T17:00:00", "scheduledStartTime": "2014-05-17T17:00:00", "tracks": [79], "races": ["2014-05-17_79_5"]}, {"id": "komb_2014-05-17_79_6", "status": "results", "startTime": "2014-05-17T17:22:00", "scheduledStartTime": "2014-05-17T17:22:00", "tracks": [79], "races": ["2014-05-17_79_6"]}, {"id": "komb_2014-05-17_79_7", "status": "results", "startTime": "2014-05-17T17:46:00", "scheduledStartTime": "2014-05-17T17:46:00", "tracks": [79], "races": ["2014-05-17_79_7"]}, {"id": "komb_2014-05-17_79_8", "status": "results", "startTime": "2014-05-17T18:10:00", "scheduledStartTime": "2014-05-17T18:10:00", "tracks": [79], "races": ["2014-05-17_79_8"]}, {"id": "komb_2014-05-17_79_9", "status": "results", "startTime": "2014-05-17T18:35:00", "scheduledStartTime": "2014-05-17T18:35:00", "tracks": [79], "races": ["2014-05-17_79_9"]}, {"id": "komb_2014-05-17_79_10", "status": "results", "startTime": "2014-05-17T18:55:00", "scheduledStartTime": "2014-05-17T18:55:00", "tracks": [79], "races": ["2014-05-17_79_10"]}], "tvilling": [{"id": "tvilling_2014-05-17_16_1", "status": "results", "startTime": "2014-05-17T12:45:13", "scheduledStartTime": "2014-05-17T12:45:00", "tracks": [16], "races": ["2014-05-17_16_1"]}, {"id": "tvilling_2014-05-17_16_2", "status": "results", "startTime": "2014-05-17T13:05:12", "scheduledStartTime": "2014-05-17T13:05:00", "tracks": [16], "races": ["2014-05-17_16_2"]}, {"id": "tvilling_2014-05-17_16_3", "status": "results", "startTime": "2014-05-17T13:26:53", "scheduledStartTime": "2014-05-17T13:25:00", "tracks": [16], "races": ["2014-05-17_16_3"]}, {"id": "tvilling_2014-05-17_16_4", "status": "results", "startTime": "2014-05-17T13:46:55", "scheduledStartTime": "2014-05-17T13:45:00", "tracks": [16], "races": ["2014-05-17_16_4"]}, {"id": "tvilling_2014-05-17_16_5", "status": "results", "startTime": "2014-05-17T14:30:35", "scheduledStartTime": "2014-05-17T14:30:00", "tracks": [16], "races": ["2014-05-17_16_5"]}, {"id": "tvilling_2014-05-17_16_6", "status": "results", "startTime": "2014-05-17T14:56:25", "scheduledStartTime": "2014-05-17T14:52:00", "tracks": [16], "races": ["2014-05-17_16_6"]}, {"id": "tvilling_2014-05-17_16_7", "status": "results", "startTime": "2014-05-17T15:16:41", "scheduledStartTime": "2014-05-17T15:15:00", "tracks": [16], "races": ["2014-05-17_16_7"]}, {"id": "tvilling_2014-05-17_16_8", "status": "results", "startTime": "2014-05-17T15:37:33", "scheduledStartTime": "2014-05-17T15:37:00", "tracks": [16], "races": ["2014-05-17_16_8"]}, {"id": "tvilling_2014-05-17_16_9", "status": "results", "startTime": "2014-05-17T15:59:13", "scheduledStartTime": "2014-05-17T15:59:00", "tracks": [16], "races": ["2014-05-17_16_9"]}, {"id": "tvilling_2014-05-17_16_10", "status": "results", "startTime": "2014-05-17T16:25:51", "scheduledStartTime": "2014-05-17T16:25:00", "tracks": [16], "races": ["2014-05-17_16_10"]}, {"id": "tvilling_2014-05-17_16_11", "status": "results", "startTime": "2014-05-17T16:48:44", "scheduledStartTime": "2014-05-17T16:48:00", "tracks": [16], "races": ["2014-05-17_16_11"]}, {"id": "tvilling_2014-05-17_16_12", "status": "results", "startTime": "2014-05-17T17:07:57", "scheduledStartTime": "2014-05-17T17:07:00", "tracks": [16], "races": ["2014-05-17_16_12"]}, {"id": "tvilling_2014-05-17_16_13", "status": "results", "startTime": "2014-05-17T17:25:25", "scheduledStartTime": "2014-05-17T17:25:00", "tracks": [16], "races": ["2014-05-17_16_13"]}, {"id": "tvilling_2014-05-17_29_1", "status": "results", "startTime": "2014-05-17T17:36:50", "scheduledStartTime": "2014-05-17T17:35:00", "tracks": [29], "races": ["2014-05-17_29_1"]}, {"id": "tvilling_2014-05-17_29_2", "status": "results", "startTime": "2014-05-17T17:57:05", "scheduledStartTime": "2014-05-17T17:55:00", "tracks": [29], "races": ["2014-05-17_29_2"]}, {"id": "tvilling_2014-05-17_29_3", "status": "results", "startTime": "2014-05-17T18:25:58", "scheduledStartTime": "2014-05-17T18:25:00", "tracks": [29], "races": ["2014-05-17_29_3"]}, {"id": "tvilling_2014-05-17_29_4", "status": "results", "startTime": "2014-05-17T18:46:29", "scheduledStartTime": "2014-05-17T18:45:00", "tracks": [29], "races": ["2014-05-17_29_4"]}, {"id": "tvilling_2014-05-17_29_5", "status": "results", "startTime": "2014-05-17T19:06:20", "scheduledStartTime": "2014-05-17T19:05:00", "tracks": [29], "races": ["2014-05-17_29_5"]}, {"id": "tvilling_2014-05-17_29_6", "status": "results", "startTime": "2014-05-17T19:26:17", "scheduledStartTime": "2014-05-17T19:25:00", "tracks": [29], "races": ["2014-05-17_29_6"]}, {"id": "tvilling_2014-05-17_29_7", "status": "results", "startTime": "2014-05-17T19:46:36", "scheduledStartTime": "2014-05-17T19:45:00", "tracks": [29], "races": ["2014-05-17_29_7"]}, {"id": "tvilling_2014-05-17_29_8", "status": "results", "startTime": "2014-05-17T20:07:04", "scheduledStartTime": "2014-05-17T20:05:00", "tracks": [29], "races": ["2014-05-17_29_8"]}, {"id": "tvilling_2014-05-17_29_9", "status": "results", "startTime": "2014-05-17T20:25:55", "scheduledStartTime": "2014-05-17T20:25:00", "tracks": [29], "races": ["2014-05-17_29_9"]}, {"id": "tvilling_2014-05-17_29_10", "status": "results", "startTime": "2014-05-17T20:51:18", "scheduledStartTime": "2014-05-17T20:45:00", "tracks": [29], "races": ["2014-05-17_29_10"]}], "vp": [{"id": "vp_2014-05-17_16_1", "status": "results", "startTime": "2014-05-17T12:45:13", "scheduledStartTime": "2014-05-17T12:45:00", "tracks": [16], "races": ["2014-05-17_16_1"]}, {"id": "vp_2014-05-17_16_2", "status": "results", "startTime": "2014-05-17T13:05:12", "scheduledStartTime": "2014-05-17T13:05:00", "tracks": [16], "races": ["2014-05-17_16_2"]}, {"id": "vp_2014-05-17_16_3", "status": "results", "startTime": "2014-05-17T13:26:53", "scheduledStartTime": "2014-05-17T13:25:00", "tracks": [16], "races": ["2014-05-17_16_3"]}, {"id": "vp_2014-05-17_16_4", "status": "results", "startTime": "2014-05-17T13:46:55", "scheduledStartTime": "2014-05-17T13:45:00", "tracks": [16], "races": ["2014-05-17_16_4"]}, {"id": "vp_2014-05-17_16_5", "status": "results", "startTime": "2014-05-17T14:30:35", "scheduledStartTime": "2014-05-17T14:30:00", "tracks": [16], "races": ["2014-05-17_16_5"]}, {"id": "vp_2014-05-17_16_6", "status": "results", "startTime": "2014-05-17T14:56:25", "scheduledStartTime": "2014-05-17T14:52:00", "tracks": [16], "races": ["2014-05-17_16_6"]}, {"id": "vp_2014-05-17_16_7", "status": "results", "startTime": "2014-05-17T15:16:41", "scheduledStartTime": "2014-05-17T15:15:00", "tracks": [16], "races": ["2014-05-17_16_7"]}, {"id": "vp_2014-05-17_16_8", "status": "results", "startTime": "2014-05-17T15:37:33", "scheduledStartTime": "2014-05-17T15:37:00", "tracks": [16], "races": ["2014-05-17_16_8"]}, {"id": "vp_2014-05-17_16_9", "status": "results", "startTime": "2014-05-17T15:59:13", "scheduledStartTime": "2014-05-17T15:59:00", "tracks": [16], "races": ["2014-05-17_16_9"]}, {"id": "vp_2014-05-17_16_10", "status": "results", "startTime": "2014-05-17T16:25:51", "scheduledStartTime": "2014-05-17T16:25:00", "tracks": [16], "races": ["2014-05-17_16_10"]}, {"id": "vp_2014-05-17_16_11", "status": "results", "startTime": "2014-05-17T16:48:44", "scheduledStartTime": "2014-05-17T16:48:00", "tracks": [16], "races": ["2014-05-17_16_11"]}, {"id": "vp_2014-05-17_16_12", "status": "results", "startTime": "2014-05-17T17:07:57", "scheduledStartTime": "2014-05-17T17:07:00", "tracks": [16], "races": ["2014-05-17_16_12"]}, {"id": "vp_2014-05-17_16_13", "status": "results", "startTime": "2014-05-17T17:25:25", "scheduledStartTime": "2014-05-17T17:25:00", "tracks": [16], "races": ["2014-05-17_16_13"]}, {"id": "vp_2014-05-17_29_1", "status": "results", "startTime": "2014-05-17T17:36:50", "scheduledStartTime": "2014-05-17T17:35:00", "tracks": [29], "races": ["2014-05-17_29_1"]}, {"id": "vp_2014-05-17_29_2", "status": "results", "startTime": "2014-05-17T17:57:05", "scheduledStartTime": "2014-05-17T17:55:00", "tracks": [29], "races": ["2014-05-17_29_2"]}, {"id": "vp_2014-05-17_29_3", "status": "results", "startTime": "2014-05-17T18:25:58", "scheduledStartTime": "2014-05-17T18:25:00", "tracks": [29], "races": ["2014-05-17_29_3"]}, {"id": "vp_2014-05-17_29_4", "status": "results", "startTime": "2014-05-17T18:46:29", "scheduledStartTime": "2014-05-17T18:45:00", "tracks": [29], "races": ["2014-05-17_29_4"]}, {"id": "vp_2014-05-17_29_5", "status": "results", "startTime": "2014-05-17T19:06:20", "scheduledStartTime": "2014-05-17T19:05:00", "tracks": [29], "races": ["2014-05-17_29_5"]}, {"id": "vp_2014-05-17_29_6", "status": "results", "startTime": "2014-05-17T19:26:17", "scheduledStartTime": "2014-05-17T19:25:00", "tracks": [29], "races": ["2014-05-17_29_6"]}, {"id": "vp_2014-05-17_29_7", "status": "results", "startTime": "2014-05-17T19:46:36", "scheduledStartTime": "2014-05-17T19:45:00", "tracks": [29], "races": ["2014-05-17_29_7"]}, {"id": "vp_2014-05-17_29_8", "status": "results", "startTime": "2014-05-17T20:07:04", "scheduledStartTime": "2014-05-17T20:05:00", "tracks": [29], "races": ["2014-05-17_29_8"]}, {"id": "vp_2014-05-17_29_9", "status": "results", "startTime": "2014-05-17T20:25:55", "scheduledStartTime": "2014-05-17T20:25:00", "tracks": [29], "races": ["2014-05-17_29_9"]}, {"id": "vp_2014-05-17_29_10", "status": "results", "startTime": "2014-05-17T20:51:18", "scheduledStartTime": "2014-05-17T20:45:00", "tracks": [29], "races": ["2014-05-17_29_10"]}, {"id": "vp_2014-05-17_79_1", "status": "results", "startTime": "2014-05-17T15:25:00", "scheduledStartTime": "2014-05-17T15:25:00", "tracks": [79], "races": ["2014-05-17_79_1"]}, {"id": "vp_2014-05-17_79_2", "status": "results", "startTime": "2014-05-17T15:50:00", "scheduledStartTime": "2014-05-17T15:50:00", "tracks": [79], "races": ["2014-05-17_79_2"]}, {"id": "vp_2014-05-17_79_3", "status": "results", "startTime": "2014-05-17T16:12:00", "scheduledStartTime": "2014-05-17T16:12:00", "tracks": [79], "races": ["2014-05-17_79_3"]}, {"id": "vp_2014-05-17_79_4", "status": "results", "startTime": "2014-05-17T16:34:00", "scheduledStartTime": "2014-05-17T16:34:00", "tracks": [79], "races": ["2014-05-17_79_4"]}, {"id": "vp_2014-05-17_79_5", "status": "results", "startTime": "2014-05-17T17:00:00", "scheduledStartTime": "2014-05-17T17:00:00", "tracks": [79], "races": ["2014-05-17_79_5"]}, {"id": "vp_2014-05-17_79_6", "status": "results", "startTime": "2014-05-17T17:22:00", "scheduledStartTime": "2014-05-17T17:22:00", "tracks": [79], "races": ["2014-05-17_79_6"]}, {"id": "vp_2014-05-17_79_7", "status": "results", "startTime": "2014-05-17T17:46:00", "scheduledStartTime": "2014-05-17T17:46:00", "tracks": [79], "races": ["2014-05-17_79_7"]}, {"id": "vp_2014-05-17_79_8", "status": "results", "startTime": "2014-05-17T18:10:00", "scheduledStartTime": "2014-05-17T18:10:00", "tracks": [79], "races": ["2014-05-17_79_8"]}, {"id": "vp_2014-05-17_79_9", "status": "results", "startTime": "2014-05-17T18:35:00", "scheduledStartTime": "2014-05-17T18:35:00", "tracks": [79], "races": ["2014-05-17_79_9"]}, {"id": "vp_2014-05-17_79_10", "status": "results", "startTime": "2014-05-17T18:55:00", "scheduledStartTime": "2014-05-17T18:55:00", "tracks": [79], "races": ["2014-05-17_79_10"]}], "vinnare": [{"id": "vinnare_2014-05-17_16_1", "status": "results", "startTime": "2014-05-17T12:45:13", "scheduledStartTime": "2014-05-17T12:45:00", "tracks": [16], "races": ["2014-05-17_16_1"]}, {"id": "vinnare_2014-05-17_16_2", "status": "results", "startTime": "2014-05-17T13:05:12", "scheduledStartTime": "2014-05-17T13:05:00", "tracks": [16], "races": ["2014-05-17_16_2"]}, {"id": "vinnare_2014-05-17_16_3", "status": "results", "startTime": "2014-05-17T13:26:53", "scheduledStartTime": "2014-05-17T13:25:00", "tracks": [16], "races": ["2014-05-17_16_3"]}, {"id": "vinnare_2014-05-17_16_4", "status": "results", "startTime": "2014-05-17T13:46:55", "scheduledStartTime": "2014-05-17T13:45:00", "tracks": [16], "races": ["2014-05-17_16_4"]}, {"id": "vinnare_2014-05-17_16_5", "status": "results", "startTime": "2014-05-17T14:30:35", "scheduledStartTime": "2014-05-17T14:30:00", "tracks": [16], "races": ["2014-05-17_16_5"]}, {"id": "vinnare_2014-05-17_16_6", "status": "results", "startTime": "2014-05-17T14:56:25", "scheduledStartTime": "2014-05-17T14:52:00", "tracks": [16], "races": ["2014-05-17_16_6"]}, {"id": "vinnare_2014-05-17_16_7", "status": "results", "startTime": "2014-05-17T15:16:41", "scheduledStartTime": "2014-05-17T15:15:00", "tracks": [16], "races": ["2014-05-17_16_7"]}, {"id": "vinnare_2014-05-17_16_8", "status": "results", "startTime": "2014-05-17T15:37:33", "scheduledStartTime": "2014-05-17T15:37:00", "tracks": [16], "races": ["2014-05-17_16_8"]}, {"id": "vinnare_2014-05-17_16_9", "status": "results", "startTime": "2014-05-17T15:59:13", "scheduledStartTime": "2014-05-17T15:59:00", "tracks": [16], "races": ["2014-05-17_16_9"]}, {"id": "vinnare_2014-05-17_16_10", "status": "results", "startTime": "2014-05-17T16:25:51", "scheduledStartTime": "2014-05-17T16:25:00", "tracks": [16], "races": ["2014-05-17_16_10"]}, {"id": "vinnare_2014-05-17_16_11", "status": "results", "startTime": "2014-05-17T16:48:44", "scheduledStartTime": "2014-05-17T16:48:00", "tracks": [16], "races": ["2014-05-17_16_11"]}, {"id": "vinnare_2014-05-17_16_12", "status": "results", "startTime": "2014-05-17T17:07:57", "scheduledStartTime": "2014-05-17T17:07:00", "tracks": [16], "races": ["2014-05-17_16_12"]}, {"id": "vinnare_2014-05-17_16_13", "status": "results", "startTime": "2014-05-17T17:25:25", "scheduledStartTime": "2014-05-17T17:25:00", "tracks": [16], "races": ["2014-05-17_16_13"]}, {"id": "vinnare_2014-05-17_29_1", "status": "results", "startTime": "2014-05-17T17:36:50", "scheduledStartTime": "2014-05-17T17:35:00", "tracks": [29], "races": ["2014-05-17_29_1"]}, {"id": "vinnare_2014-05-17_29_2", "status": "results", "startTime": "2014-05-17T17:57:05", "scheduledStartTime": "2014-05-17T17:55:00", "tracks": [29], "races": ["2014-05-17_29_2"]}, {"id": "vinnare_2014-05-17_29_3", "status": "results", "startTime": "2014-05-17T18:25:58", "scheduledStartTime": "2014-05-17T18:25:00", "tracks": [29], "races": ["2014-05-17_29_3"]}, {"id": "vinnare_2014-05-17_29_4", "status": "results", "startTime": "2014-05-17T18:46:29", "scheduledStartTime": "2014-05-17T18:45:00", "tracks": [29], "races": ["2014-05-17_29_4"]}, {"id": "vinnare_2014-05-17_29_5", "status": "results", "startTime": "2014-05-17T19:06:20", "scheduledStartTime": "2014-05-17T19:05:00", "tracks": [29], "races": ["2014-05-17_29_5"]}, {"id": "vinnare_2014-05-17_29_6", "status": "results", "startTime": "2014-05-17T19:26:17", "scheduledStartTime": "2014-05-17T19:25:00", "tracks": [29], "races": ["2014-05-17_29_6"]}, {"id": "vinnare_2014-05-17_29_7", "status": "results", "startTime": "2014-05-17T19:46:36", "scheduledStartTime": "2014-05-17T19:45:00", "tracks": [29], "races": ["2014-05-17_29_7"]}, {"id": "vinnare_2014-05-17_29_8", "status": "results", "startTime": "2014-05-17T20:07:04", "scheduledStartTime": "2014-05-17T20:05:00", "tracks": [29], "races": ["2014-05-17_29_8"]}, {"id": "vinnare_2014-05-17_29_9", "status": "results", "startTime": "2014-05-17T20:25:55", "scheduledStartTime": "2014-05-17T20:25:00", "tracks": [29], "races": ["2014-05-17_29_9"]}, {"id": "vinnare_2014-05-17_29_10", "status": "results", "startTime": "2014-05-17T20:51:18", "scheduledStartTime": "2014-05-17T20:45:00", "tracks": [29], "races": ["2014-05-17_29_10"]}, {"id": "vinnare_2014-05-17_79_1", "status": "results", "startTime": "2014-05-17T15:25:00", "scheduledStartTime": "2014-05-17T15:25:00", "tracks": [79], "races": ["2014-05-17_79_1"]}, {"id": "vinnare_2014-05-17_79_2", "status": "results", "startTime": "2014-05-17T15:50:00", "scheduledStartTime": "2014-05-17T15:50:00", "tracks": [79], "races": ["2014-05-17_79_2"]}, {"id": "vinnare_2014-05-17_79_3", "status": "results", "startTime": "2014-05-17T16:12:00", "scheduledStartTime": "2014-05-17T16:12:00", "tracks": [79], "races": ["2014-05-17_79_3"]}, {"id": "vinnare_2014-05-17_79_4", "status": "results", "startTime": "2014-05-17T16:34:00", "scheduledStartTime": "2014-05-17T16:34:00", "tracks": [79], "races": ["2014-05-17_79_4"]}, {"id": "vinnare_2014-05-17_79_5", "status": "results", "startTime": "2014-05-17T17:00:00", "scheduledStartTime": "2014-05-17T17:00:00", "tracks": [79], "races": ["2014-05-17_79_5"]}, {"id": "vinnare_2014-05-17_79_6", "status": "results", "startTime": "2014-05-17T17:22:00", "scheduledStartTime": "2014-05-17T17:22:00", "tracks": [79], "races": ["2014-05-17_79_6"]}, {"id": "vinnare_2014-05-17_79_7", "status": "results", "startTime": "2014-05-17T17:46:00", "scheduledStartTime": "2014-05-17T17:46:00", "tracks": [79], "races": ["2014-05-17_79_7"]}, {"id": "vinnare_2014-05-17_79_8", "status": "results", "startTime": "2014-05-17T18:10:00", "scheduledStartTime": "2014-05-17T18:10:00", "tracks": [79], "races": ["2014-05-17_79_8"]}, {"id": "vinnare_2014-05-17_79_9", "status": "results", "startTime": "2014-05-17T18:35:00", "scheduledStartTime": "2014-05-17T18:35:00", "tracks": [79], "races": ["2014-05-17_79_9"]}, {"id": "vinnare_2014-05-17_79_10", "status": "results", "startTime": "2014-05-17T18:55:00", "scheduledStartTime": "2014-05-17T18:55:00", "tracks": [79], "races": ["2014-05-17_79_10"]}], "plats": [{"id": "plats_2014-05-17_16_1", "status": "results", "startTime": "2014-05-17T12:45:13", "scheduledStartTime": "2014-05-17T12:45:00", "tracks": [16], "races": ["2014-05-17_16_1"]}, {"id": "plats_2014-05-17_16_2", "status": "results", "startTime": "2014-05-17T13:05:12", "scheduledStartTime": "2014-05-17T13:05:00", "tracks": [16], "races": ["2014-05-17_16_2"]}, {"id": "plats_2014-05-17_16_3", "status": "results", "startTime": "2014-05-17T13:26:53", "scheduledStartTime": "2014-05-17T13:25:00", "tracks": [16], "races": ["2014-05-17_16_3"]}, {"id": "plats_2014-05-17_16_4", "status": "results", "startTime": "2014-05-17T13:46:55", "scheduledStartTime": "2014-05-17T13:45:00", "tracks": [16], "races": ["2014-05-17_16_4"]}, {"id": "plats_2014-05-17_16_5", "status": "results", "startTime": "2014-05-17T14:30:35", "scheduledStartTime": "2014-05-17T14:30:00", "tracks": [16], "races": ["2014-05-17_16_5"]}, {"id": "plats_2014-05-17_16_6", "status": "results", "startTime": "2014-05-17T14:56:25", "scheduledStartTime": "2014-05-17T14:52:00", "tracks": [16], "races": ["2014-05-17_16_6"]}, {"id": "plats_2014-05-17_16_7", "status": "results", "startTime": "2014-05-17T15:16:41", "scheduledStartTime": "2014-05-17T15:15:00", "tracks": [16], "races": ["2014-05-17_16_7"]}, {"id": "plats_2014-05-17_16_8", "status": "results", "startTime": "2014-05-17T15:37:33", "scheduledStartTime": "2014-05-17T15:37:00", "tracks": [16], "races": ["2014-05-17_16_8"]}, {"id": "plats_2014-05-17_16_9", "status": "results", "startTime": "2014-05-17T15:59:13", "scheduledStartTime": "2014-05-17T15:59:00", "tracks": [16], "races": ["2014-05-17_16_9"]}, {"id": "plats_2014-05-17_16_10", "status": "results", "startTime": "2014-05-17T16:25:51", "scheduledStartTime": "2014-05-17T16:25:00", "tracks": [16], "races": ["2014-05-17_16_10"]}, {"id": "plats_2014-05-17_16_11", "status": "results", "startTime": "2014-05-17T16:48:44", "scheduledStartTime": "2014-05-17T16:48:00", "tracks": [16], "races": ["2014-05-17_16_11"]}, {"id": "plats_2014-05-17_16_12", "status": "results", "startTime": "2014-05-17T17:07:57", "scheduledStartTime": "2014-05-17T17:07:00", "tracks": [16], "races": ["2014-05-17_16_12"]}, {"id": "plats_2014-05-17_16_13", "status": "results", "startTime": "2014-05-17T17:25:25", "scheduledStartTime": "2014-05-17T17:25:00", "tracks": [16], "races": ["2014-05-17_16_13"]}, {"id": "plats_2014-05-17_29_1", "status": "results", "startTime": "2014-05-17T17:36:50", "scheduledStartTime": "2014-05-17T17:35:00", "tracks": [29], "races": ["2014-05-17_29_1"]}, {"id": "plats_2014-05-17_29_2", "status": "results", "startTime": "2014-05-17T17:57:05", "scheduledStartTime": "2014-05-17T17:55:00", "tracks": [29], "races": ["2014-05-17_29_2"]}, {"id": "plats_2014-05-17_29_3", "status": "results", "startTime": "2014-05-17T18:25:58", "scheduledStartTime": "2014-05-17T18:25:00", "tracks": [29], "races": ["2014-05-17_29_3"]}, {"id": "plats_2014-05-17_29_4", "status": "results", "startTime": "2014-05-17T18:46:29", "scheduledStartTime": "2014-05-17T18:45:00", "tracks": [29], "races": ["2014-05-17_29_4"]}, {"id": "plats_2014-05-17_29_5", "status": "results", "startTime": "2014-05-17T19:06:20", "scheduledStartTime": "2014-05-17T19:05:00", "tracks": [29], "races": ["2014-05-17_29_5"]}, {"id": "plats_2014-05-17_29_6", "status": "results", "startTime": "2014-05-17T19:26:17", "scheduledStartTime": "2014-05-17T19:25:00", "tracks": [29], "races": ["2014-05-17_29_6"]}, {"id": "plats_2014-05-17_29_7", "status": "results", "startTime": "2014-05-17T19:46:36", "scheduledStartTime": "2014-05-17T19:45:00", "tracks": [29], "races": ["2014-05-17_29_7"]}, {"id": "plats_2014-05-17_29_8", "status": "results", "startTime": "2014-05-17T20:07:04", "scheduledStartTime": "2014-05-17T20:05:00", "tracks": [29], "races": ["2014-05-17_29_8"]}, {"id": "plats_2014-05-17_29_9", "status": "results", "startTime": "2014-05-17T20:25:55", "scheduledStartTime": "2014-05-17T20:25:00", "tracks": [29], "races": ["2014-05-17_29_9"]}, {"id": "plats_2014-05-17_29_10", "status": "results", "startTime": "2014-05-17T20:51:18", "scheduledStartTime": "2014-05-17T20:45:00", "tracks": [29], "races": ["2014-05-17_29_10"]}, {"id": "plats_2014-05-17_79_1", "status": "results", "startTime": "2014-05-17T15:25:00", "scheduledStartTime": "2014-05-17T15:25:00", "tracks": [79], "races": ["2014-05-17_79_1"]}, {"id": "plats_2014-05-17_79_2", "status": "results", "startTime": "2014-05-17T15:50:00", "scheduledStartTime": "2014-05-17T15:50:00", "tracks": [79], "races": ["2014-05-17_79_2"]}, {"id": "plats_2014-05-17_79_3", "status": "results", "startTime": "2014-05-17T16:12:00", "scheduledStartTime": "2014-05-17T16:12:00", "tracks": [79], "races": ["2014-05-17_79_3"]}, {"id": "plats_2014-05-17_79_4", "status": "results", "startTime": "2014-05-17T16:34:00", "scheduledStartTime": "2014-05-17T16:34:00", "tracks": [79], "races": ["2014-05-17_79_4"]}, {"id": "plats_2014-05-17_79_5", "status": "results", "startTime": "2014-05-17T17:00:00", "scheduledStartTime": "2014-05-17T17:00:00", "tracks": [79], "races": ["2014-05-17_79_5"]}, {"id": "plats_2014-05-17_79_6", "status": "results", "startTime": "2014-05-17T17:22:00", "scheduledStartTime": "2014-05-17T17:22:00", "tracks": [79], "races": ["2014-05-17_79_6"]}, {"id": "plats_2014-05-17_79_7", "status": "results", "startTime": "2014-05-17T17:46:00", "scheduledStartTime": "2014-05-17T17:46:00", "tracks": [79], "races": ["2014-05-17_79_7"]}, {"id": "plats_2014-05-17_79_8", "status": "results", "startTime": "2014-05-17T18:10:00", "scheduledStartTime": "2014-05-17T18:10:00", "tracks": [79], "races": ["2014-05-17_79_8"]}, {"id": "plats_2014-05-17_79_9", "status": "results", "startTime": "2014-05-17T18:35:00", "scheduledStartTime": "2014-05-17T18:35:00", "tracks": [79], "races": ["2014-05-17_79_9"]}, {"id": "plats_2014-05-17_79_10", "status": "results", "startTime": "2014-05-17T18:55:00", "scheduledStartTime": "2014-05-17T18:55:00", "tracks": [79], "races": ["2014-05-17_79_10"]}], "raket": [{"id": "raket_2014-05-17_16_1", "status": "results", "startTime": "2014-05-17T12:45:13", "scheduledStartTime": "2014-05-17T12:45:00", "tracks": [16], "races": ["2014-05-17_16_1", "2014-05-17_16_2", "2014-05-17_16_3", "2014-05-17_16_4", "2014-05-17_16_5", "2014-05-17_16_6", "2014-05-17_16_7", "2014-05-17_16_8", "2014-05-17_16_9", "2014-05-17_16_10", "2014-05-17_16_11", "2014-05-17_16_12", "2014-05-17_16_13"]}, {"id": "raket_2014-05-17_29_1", "status": "results", "startTime": "2014-05-17T17:36:50", "scheduledStartTime": "2014-05-17T17:35:00", "tracks": [29], "races": ["2014-05-17_29_1", "2014-05-17_29_2", "2014-05-17_29_3", "2014-05-17_29_4", "2014-05-17_29_5", "2014-05-17_29_6", "2014-05-17_29_7", "2014-05-17_29_8", "2014-05-17_29_9", "2014-05-17_29_10"]}, {"id": "raket_2014-05-17_79_1", "status": "results", "startTime": "2014-05-17T15:25:00", "scheduledStartTime": "2014-05-17T15:25:00", "tracks": [79], "races": ["2014-05-17_79_1", "2014-05-17_79_2", "2014-05-17_79_3", "2014-05-17_79_4", "2014-05-17_79_5", "2014-05-17_79_6", "2014-05-17_79_7", "2014-05-17_79_8", "2014-05-17_79_9", "2014-05-17_79_10"]}]}, "currentVersion": 1516648137588}