{"date": "2017-07-20", "tracks": [{"id": 9, "name": "Bergs\u00e5ker", "startTime": "2017-07-20T18:15:00", "races": [{"id": "2017-07-20_9_1", "number": 1, "status": "results", "startTime": "2017-07-20T18:15:14"}, {"id": "2017-07-20_9_2", "number": 2, "status": "results", "startTime": "2017-07-20T18:37:36"}, {"id": "2017-07-20_9_3", "number": 3, "status": "results", "startTime": "2017-07-20T19:00:44"}, {"id": "2017-07-20_9_4", "number": 4, "status": "results", "startTime": "2017-07-20T19:25:07"}, {"id": "2017-07-20_9_5", "number": 5, "status": "results", "startTime": "2017-07-20T19:48:21"}, {"id": "2017-07-20_9_6", "number": 6, "status": "results", "startTime": "2017-07-20T20:09:12"}, {"id": "2017-07-20_9_7", "number": 7, "status": "results", "startTime": "2017-07-20T20:35:29"}, {"id": "2017-07-20_9_8", "number": 8, "status": "results", "startTime": "2017-07-20T20:54:49"}, {"id": "2017-07-20_9_9", "number": 9, "status": "results", "startTime": "2017-07-20T21:15:26"}, {"id": "2017-07-20_9_10", "number": 10, "status": "results", "startTime": "2017-07-20T21:35:34"}, {"id": "2017-07-20_9_11", "number": 11, "status": "results", "startTime": "2017-07-20T21:51:00"}, {"id": "2017-07-20_9_12", "number": 12, "status": "results", "startTime": "2017-07-20T22:07:02"}], "sport": "trot", "biggestGameType": "V64"}, {"id": 79, "name": "\u00d6vrevoll", "startTime": "2017-07-20T18:30:00", "races": [{"id": "2017-07-20_79_1", "number": 1, "status": "results", "startTime": "2017-07-20T18:32:21"}, {"id": "2017-07-20_79_2", "number": 2, "status": "results", "startTime": "2017-07-20T19:03:14"}, {"id": "2017-07-20_79_3", "number": 3, "status": "results", "startTime": "2017-07-20T19:28:38"}, {"id": "2017-07-20_79_4", "number": 4, "status": "results", "startTime": "2017-07-20T19:47:02"}, {"id": "2017-07-20_79_5", "number": 5, "status": "results", "startTime": "2017-07-20T20:11:54"}, {"id": "2017-07-20_79_6", "number": 6, "status": "results", "startTime": "2017-07-20T20:38:06"}, {"id": "2017-07-20_79_7", "number": 7, "status": "results", "startTime": "2017-07-20T21:06:34"}, {"id": "2017-07-20_79_8", "number": 8, "status": "results", "startTime": "2017-07-20T21:25:18"}], "sport": "gallop", "biggestGameType": "V65"}, {"id": 32, "name": "\u00d6rebro", "startTime": "2017-07-20T18:25:00", "races": [{"id": "2017-07-20_32_1", "number": 1, "status": "results", "startTime": "2017-07-20T18:25:58"}, {"id": "2017-07-20_32_2", "number": 2, "status": "results", "startTime": "2017-07-20T18:48:20"}, {"id": "2017-07-20_32_3", "number": 3, "status": "results", "startTime": "2017-07-20T19:11:15"}, {"id": "2017-07-20_32_4", "number": 4, "status": "results", "startTime": "2017-07-20T19:39:20"}, {"id": "2017-07-20_32_5", "number": 5, "status": "results", "startTime": "2017-07-20T19:59:04"}, {"id": "2017-07-20_32_6", "number": 6, "status": "results", "startTime": "2017-07-20T20:20:35"}, {"id": "2017-07-20_32_7", "number": 7, "status": "results", "startTime": "2017-07-20T20:42:55"}, {"id": "2017-07-20_32_8", "number": 8, "status": "results", "startTime": "2017-07-20T21:06:29"}, {"id": "2017-07-20_32_9", "number": 9, "status": "results", "startTime": "2017-07-20T21:25:08"}, {"id": "2017-07-20_32_10", "number": 10, "status": "results", "startTime": "2017-07-20T21:45:12"}], "sport": "trot", "biggestGameType": "V5"}, {"id": 44, "name": "Karlshamn", "startTime": "2017-07-20T12:20:00", "races": [{"id": "2017-07-20_44_1", "number": 1, "status": "results", "startTime": "2017-07-20T12:20:46"}, {"id": "2017-07-20_44_2", "number": 2, "status": "results", "startTime": "2017-07-20T12:40:24"}, {"id": "2017-07-20_44_3", "number": 3, "status": "results", "startTime": "2017-07-20T13:00:23"}, {"id": "2017-07-20_44_4", "number": 4, "status": "results", "startTime": "2017-07-20T13:20:23"}, {"id": "2017-07-20_44_5", "number": 5, "status": "results", "startTime": "2017-07-20T14:00:45"}, {"id": "2017-07-20_44_6", "number": 6, "status": "results", "startTime": "2017-07-20T14:20:22"}, {"id": "2017-07-20_44_7", "number": 7, "status": "results", "startTime": "2017-07-20T14:40:26"}, {"id": "2017-07-20_44_8", "number": 8, "status": "results", "startTime": "2017-07-20T15:00:55"}, {"id": "2017-07-20_44_9", "number": 9, "status": "results", "startTime": "2017-07-20T15:20:28"}], "sport": "trot", "biggestGameType": "V4"}, {"id": 78, "name": "Bjerke", "startTime": "2017-07-20T13:40:00", "races": [{"id": "2017-07-20_78_1", "number": 1, "status": "results", "startTime": "2017-07-20T13:40:46"}, {"id": "2017-07-20_78_2", "number": 2, "status": "results", "startTime": "2017-07-20T13:58:57"}, {"id": "2017-07-20_78_3", "number": 3, "status": "results", "startTime": "2017-07-20T14:10:45"}, {"id": "2017-07-20_78_4", "number": 4, "status": "results", "startTime": "2017-07-20T14:23:58"}, {"id": "2017-07-20_78_5", "number": 5, "status": "results", "startTime": "2017-07-20T14:35:42"}], "sport": "trot", "biggestGameType": "V5"}, {"id": 86, "name": "Hamburg-Bahrenfeld", "startTime": "2017-07-20T18:30:00", "races": [{"id": "2017-07-20_86_1", "number": 1, "status": "results", "startTime": "2017-07-20T18:31:20"}, {"id": "2017-07-20_86_2", "number": 2, "status": "results", "startTime": "2017-07-20T18:56:25"}, {"id": "2017-07-20_86_3", "number": 3, "status": "results", "startTime": "2017-07-20T19:20:22"}, {"id": "2017-07-20_86_4", "number": 4, "status": "results", "startTime": "2017-07-20T19:45:51"}, {"id": "2017-07-20_86_5", "number": 5, "status": "results", "startTime": "2017-07-20T20:14:09"}, {"id": "2017-07-20_86_6", "number": 6, "status": "results", "startTime": "2017-07-20T20:40:09"}, {"id": "2017-07-20_86_7", "number": 7, "status": "results", "startTime": "2017-07-20T21:05:27"}, {"id": "2017-07-20_86_8", "number": 8, "status": "results", "startTime": "2017-07-20T21:30:11"}, {"id": "2017-07-20_86_9", "number": 9, "status": "results", "startTime": "2017-07-20T21:52:28"}, {"id": "2017-07-20_86_10", "number": 10, "status": "results", "startTime": "2017-07-20T22:21:23"}], "sport": "trot", "biggestGameType": "V5"}, {"id": 51, "name": "Australien", "startTime": "2017-07-20T09:58:00", "races": [{"id": "2017-07-20_51_1", "number": 1, "status": "results", "startTime": "2017-07-20T09:33:07"}, {"id": "2017-07-20_51_2", "number": 2, "status": "results", "startTime": "2017-07-20T09:58:58"}, {"id": "2017-07-20_51_3", "number": 3, "status": "results", "startTime": "2017-07-20T10:33:08"}, {"id": "2017-07-20_51_4", "number": 4, "status": "results", "startTime": "2017-07-20T11:01:08"}, {"id": "2017-07-20_51_5", "number": 5, "status": "results", "startTime": "2017-07-20T11:31:10"}, {"id": "2017-07-20_51_6", "number": 6, "status": "results", "startTime": "2017-07-20T12:01:22"}, {"id": "2017-07-20_51_7", "number": 7, "status": "results", "startTime": "2017-07-20T12:31:00"}, {"id": "2017-07-20_51_8", "number": 8, "status": "results", "startTime": "2017-07-20T13:00:54"}, {"id": "2017-07-20_51_9", "number": 9, "status": "results", "startTime": "2017-07-20T13:31:30"}, {"id": "2017-07-20_51_10", "number": 10, "status": "results", "startTime": "2017-07-20T14:00:51"}], "sport": "trot", "biggestGameType": "V4"}, {"id": 89, "name": "Sydafrika", "startTime": "2017-07-20T12:10:00", "races": [{"id": "2017-07-20_89_1", "number": 1, "status": "results", "startTime": "2017-07-20T12:10:31"}, {"id": "2017-07-20_89_2", "number": 2, "status": "results", "startTime": "2017-07-20T12:45:49"}, {"id": "2017-07-20_89_3", "number": 3, "status": "results", "startTime": "2017-07-20T13:21:01"}, {"id": "2017-07-20_89_4", "number": 4, "status": "results", "startTime": "2017-07-20T13:55:46"}, {"id": "2017-07-20_89_5", "number": 5, "status": "results", "startTime": "2017-07-20T14:34:09"}, {"id": "2017-07-20_89_6", "number": 6, "status": "results", "startTime": "2017-07-20T15:06:18"}, {"id": "2017-07-20_89_7", "number": 7, "status": "results", "startTime": "2017-07-20T15:43:54"}, {"id": "2017-07-20_89_8", "number": 8, "status": "results", "startTime": "2017-07-20T16:20:56"}, {"id": "2017-07-20_89_9", "number": 9, "status": "results", "startTime": "2017-07-20T16:56:10"}], "sport": "gallop", "biggestGameType": "trio"}], "games": {"V64": [{"id": "V64_2017-07-20_9_4", "status": "results", "startTime": "2017-07-20T19:25:07", "scheduledStartTime": "2017-07-20T19:25:00", "tracks": [9], "races": ["2017-07-20_9_4", "2017-07-20_9_5", "2017-07-20_9_6", "2017-07-20_9_7", "2017-07-20_9_8", "2017-07-20_9_9"]}], "V65": [{"id": "V65_2017-07-20_79_3", "status": "results", "startTime": "2017-07-20T19:28:38", "scheduledStartTime": "2017-07-20T19:25:00", "tracks": [79], "jackpotAmount": 364469, "races": ["2017-07-20_79_3", "2017-07-20_79_4", "2017-07-20_79_5", "2017-07-20_79_6", "2017-07-20_79_7", "2017-07-20_79_8"]}], "V5": [{"id": "V5_2017-07-20_32_5", "status": "results", "startTime": "2017-07-20T19:59:04", "scheduledStartTime": "2017-07-20T19:58:00", "tracks": [32], "races": ["2017-07-20_32_5", "2017-07-20_32_6", "2017-07-20_32_7", "2017-07-20_32_8", "2017-07-20_32_9"]}, {"id": "V5_2017-07-20_44_5", "status": "results", "startTime": "2017-07-20T14:00:45", "scheduledStartTime": "2017-07-20T14:00:00", "tracks": [44], "races": ["2017-07-20_44_5", "2017-07-20_44_6", "2017-07-20_44_7", "2017-07-20_44_8", "2017-07-20_44_9"]}, {"id": "V5_2017-07-20_78_1", "status": "results", "startTime": "2017-07-20T13:40:46", "scheduledStartTime": "2017-07-20T13:40:00", "tracks": [78], "races": ["2017-07-20_78_1", "2017-07-20_78_2", "2017-07-20_78_3", "2017-07-20_78_4", "2017-07-20_78_5"]}, {"id": "V5_2017-07-20_86_5", "status": "results", "startTime": "2017-07-20T20:14:09", "scheduledStartTime": "2017-07-20T20:06:00", "tracks": [86], "races": ["2017-07-20_86_5", "2017-07-20_86_6", "2017-07-20_86_7", "2017-07-20_86_8", "2017-07-20_86_9"]}], "V4": [{"id": "V4_2017-07-20_9_6", "status": "results", "startTime": "2017-07-20T20:09:12", "scheduledStartTime": "2017-07-20T20:09:00", "tracks": [9], "races": ["2017-07-20_9_6", "2017-07-20_9_7", "2017-07-20_9_8", "2017-07-20_9_9"]}, {"id": "V4_2017-07-20_32_3", "status": "results", "startTime": "2017-07-20T19:11:15", "scheduledStartTime": "2017-07-20T19:11:00", "tracks": [32], "races": ["2017-07-20_32_3", "2017-07-20_32_4", "2017-07-20_32_5", "2017-07-20_32_6"]}, {"id": "V4_2017-07-20_44_1", "status": "results", "startTime": "2017-07-20T12:20:46", "scheduledStartTime": "2017-07-20T12:20:00", "tracks": [44], "races": ["2017-07-20_44_1", "2017-07-20_44_2", "2017-07-20_44_3", "2017-07-20_44_4"]}, {"id": "V4_2017-07-20_51_1", "status": "results", "startTime": "2017-07-20T09:33:07", "scheduledStartTime": "2017-07-20T09:32:00", "tracks": [51], "races": ["2017-07-20_51_1", "2017-07-20_51_2", "2017-07-20_51_3", "2017-07-20_51_4"]}, {"id": "V4_2017-07-20_79_5", "status": "results", "startTime": "2017-07-20T20:11:54", "scheduledStartTime": "2017-07-20T20:10:00", "tracks": [79], "races": ["2017-07-20_79_5", "2017-07-20_79_6", "2017-07-20_79_7", "2017-07-20_79_8"]}], "V3": [{"id": "V3_2017-07-20_9_10", "status": "results", "startTime": "2017-07-20T21:35:34", "scheduledStartTime": "2017-07-20T21:31:00", "tracks": [9], "races": ["2017-07-20_9_10", "2017-07-20_9_11", "2017-07-20_9_12"]}, {"id": "V3_2017-07-20_32_8", "status": "results", "startTime": "2017-07-20T21:06:29", "scheduledStartTime": "2017-07-20T21:03:00", "tracks": [32], "races": ["2017-07-20_32_8", "2017-07-20_32_9", "2017-07-20_32_10"]}, {"id": "V3_2017-07-20_44_7", "status": "results", "startTime": "2017-07-20T14:40:26", "scheduledStartTime": "2017-07-20T14:40:00", "tracks": [44], "races": ["2017-07-20_44_7", "2017-07-20_44_8", "2017-07-20_44_9"]}], "dd": [{"id": "dd_2017-07-20_9_8", "status": "results", "startTime": "2017-07-20T20:54:49", "scheduledStartTime": "2017-07-20T20:53:00", "tracks": [9], "races": ["2017-07-20_9_8", "2017-07-20_9_9"]}], "ld": [{"id": "ld_2017-07-20_44_3", "status": "results", "startTime": "2017-07-20T13:00:23", "scheduledStartTime": "2017-07-20T13:00:00", "tracks": [44], "races": ["2017-07-20_44_3", "2017-07-20_44_4"]}], "trio": [{"id": "trio_2017-07-20_9_1", "status": "results", "startTime": "2017-07-20T18:15:14", "scheduledStartTime": "2017-07-20T18:15:00", "tracks": [9], "races": ["2017-07-20_9_1"]}, {"id": "trio_2017-07-20_9_2", "status": "results", "startTime": "2017-07-20T18:37:36", "scheduledStartTime": "2017-07-20T18:37:00", "tracks": [9], "races": ["2017-07-20_9_2"]}, {"id": "trio_2017-07-20_9_3", "status": "results", "startTime": "2017-07-20T19:00:44", "scheduledStartTime": "2017-07-20T19:00:00", "tracks": [9], "races": ["2017-07-20_9_3"]}, {"id": "trio_2017-07-20_9_4", "status": "results", "startTime": "2017-07-20T19:25:07", "scheduledStartTime": "2017-07-20T19:25:00", "tracks": [9], "races": ["2017-07-20_9_4"]}, {"id": "trio_2017-07-20_9_5", "status": "results", "startTime": "2017-07-20T19:48:21", "scheduledStartTime": "2017-07-20T19:47:00", "tracks": [9], "races": ["2017-07-20_9_5"]}, {"id": "trio_2017-07-20_9_6", "status": "results", "startTime": "2017-07-20T20:09:12", "scheduledStartTime": "2017-07-20T20:09:00", "tracks": [9], "races": ["2017-07-20_9_6"]}, {"id": "trio_2017-07-20_9_7", "status": "results", "startTime": "2017-07-20T20:35:29", "scheduledStartTime": "2017-07-20T20:31:00", "tracks": [9], "races": ["2017-07-20_9_7"]}, {"id": "trio_2017-07-20_9_8", "status": "results", "startTime": "2017-07-20T20:54:49", "scheduledStartTime": "2017-07-20T20:53:00", "tracks": [9], "races": ["2017-07-20_9_8"]}, {"id": "trio_2017-07-20_9_9", "status": "results", "startTime": "2017-07-20T21:15:26", "scheduledStartTime": "2017-07-20T21:13:00", "tracks": [9], "races": ["2017-07-20_9_9"]}, {"id": "trio_2017-07-20_9_10", "status": "results", "startTime": "2017-07-20T21:35:34", "scheduledStartTime": "2017-07-20T21:31:00", "tracks": [9], "races": ["2017-07-20_9_10"]}, {"id": "trio_2017-07-20_9_11", "status": "results", "startTime": "2017-07-20T21:51:00", "scheduledStartTime": "2017-07-20T21:48:00", "tracks": [9], "races": ["2017-07-20_9_11"]}, {"id": "trio_2017-07-20_9_12", "status": "results", "startTime": "2017-07-20T22:07:02", "scheduledStartTime": "2017-07-20T22:04:00", "tracks": [9], "races": ["2017-07-20_9_12"]}, {"id": "trio_2017-07-20_32_1", "status": "results", "startTime": "2017-07-20T18:25:58", "scheduledStartTime": "2017-07-20T18:25:00", "tracks": [32], "races": ["2017-07-20_32_1"]}, {"id": "trio_2017-07-20_32_2", "status": "results", "startTime": "2017-07-20T18:48:20", "scheduledStartTime": "2017-07-20T18:48:00", "tracks": [32], "races": ["2017-07-20_32_2"]}, {"id": "trio_2017-07-20_32_3", "status": "results", "startTime": "2017-07-20T19:11:15", "scheduledStartTime": "2017-07-20T19:11:00", "tracks": [32], "races": ["2017-07-20_32_3"]}, {"id": "trio_2017-07-20_32_4", "status": "results", "startTime": "2017-07-20T19:39:20", "scheduledStartTime": "2017-07-20T19:35:00", "tracks": [32], "races": ["2017-07-20_32_4"]}, {"id": "trio_2017-07-20_32_5", "status": "results", "startTime": "2017-07-20T19:59:04", "scheduledStartTime": "2017-07-20T19:58:00", "tracks": [32], "races": ["2017-07-20_32_5"]}, {"id": "trio_2017-07-20_32_6", "status": "results", "startTime": "2017-07-20T20:20:35", "scheduledStartTime": "2017-07-20T20:20:00", "tracks": [32], "races": ["2017-07-20_32_6"]}, {"id": "trio_2017-07-20_32_7", "status": "results", "startTime": "2017-07-20T20:42:55", "scheduledStartTime": "2017-07-20T20:42:00", "tracks": [32], "races": ["2017-07-20_32_7"]}, {"id": "trio_2017-07-20_32_8", "status": "results", "startTime": "2017-07-20T21:06:29", "scheduledStartTime": "2017-07-20T21:03:00", "tracks": [32], "races": ["2017-07-20_32_8"]}, {"id": "trio_2017-07-20_32_9", "status": "results", "startTime": "2017-07-20T21:25:08", "scheduledStartTime": "2017-07-20T21:21:00", "tracks": [32], "races": ["2017-07-20_32_9"]}, {"id": "trio_2017-07-20_32_10", "status": "results", "startTime": "2017-07-20T21:45:12", "scheduledStartTime": "2017-07-20T21:38:00", "tracks": [32], "races": ["2017-07-20_32_10"]}, {"id": "trio_2017-07-20_44_1", "status": "results", "startTime": "2017-07-20T12:20:46", "scheduledStartTime": "2017-07-20T12:20:00", "tracks": [44], "races": ["2017-07-20_44_1"]}, {"id": "trio_2017-07-20_44_2", "status": "results", "startTime": "2017-07-20T12:40:24", "scheduledStartTime": "2017-07-20T12:40:00", "tracks": [44], "races": ["2017-07-20_44_2"]}, {"id": "trio_2017-07-20_44_3", "status": "results", "startTime": "2017-07-20T13:00:23", "scheduledStartTime": "2017-07-20T13:00:00", "tracks": [44], "races": ["2017-07-20_44_3"]}, {"id": "trio_2017-07-20_44_4", "status": "results", "startTime": "2017-07-20T13:20:23", "scheduledStartTime": "2017-07-20T13:20:00", "tracks": [44], "races": ["2017-07-20_44_4"]}, {"id": "trio_2017-07-20_44_5", "status": "results", "startTime": "2017-07-20T14:00:45", "scheduledStartTime": "2017-07-20T14:00:00", "tracks": [44], "races": ["2017-07-20_44_5"]}, {"id": "trio_2017-07-20_44_6", "status": "results", "startTime": "2017-07-20T14:20:22", "scheduledStartTime": "2017-07-20T14:20:00", "tracks": [44], "races": ["2017-07-20_44_6"]}, {"id": "trio_2017-07-20_44_7", "status": "results", "startTime": "2017-07-20T14:40:26", "scheduledStartTime": "2017-07-20T14:40:00", "tracks": [44], "races": ["2017-07-20_44_7"]}, {"id": "trio_2017-07-20_44_8", "status": "results", "startTime": "2017-07-20T15:00:55", "scheduledStartTime": "2017-07-20T15:00:00", "tracks": [44], "races": ["2017-07-20_44_8"]}, {"id": "trio_2017-07-20_44_9", "status": "results", "startTime": "2017-07-20T15:20:28", "scheduledStartTime": "2017-07-20T15:20:00", "tracks": [44], "races": ["2017-07-20_44_9"]}, {"id": "trio_2017-07-20_78_1", "status": "results", "startTime": "2017-07-20T13:40:46", "scheduledStartTime": "2017-07-20T13:40:00", "tracks": [78], "races": ["2017-07-20_78_1"]}, {"id": "trio_2017-07-20_78_2", "status": "results", "startTime": "2017-07-20T13:58:57", "scheduledStartTime": "2017-07-20T13:58:00", "tracks": [78], "races": ["2017-07-20_78_2"]}, {"id": "trio_2017-07-20_78_3", "status": "results", "startTime": "2017-07-20T14:10:45", "scheduledStartTime": "2017-07-20T14:10:00", "tracks": [78], "races": ["2017-07-20_78_3"]}, {"id": "trio_2017-07-20_78_4", "status": "results", "startTime": "2017-07-20T14:23:58", "scheduledStartTime": "2017-07-20T14:22:00", "tracks": [78], "races": ["2017-07-20_78_4"]}, {"id": "trio_2017-07-20_78_5", "status": "results", "startTime": "2017-07-20T14:35:42", "scheduledStartTime": "2017-07-20T14:34:00", "tracks": [78], "races": ["2017-07-20_78_5"]}, {"id": "trio_2017-07-20_79_1", "status": "results", "startTime": "2017-07-20T18:32:21", "scheduledStartTime": "2017-07-20T18:30:00", "tracks": [79], "races": ["2017-07-20_79_1"]}, {"id": "trio_2017-07-20_79_2", "status": "results", "startTime": "2017-07-20T19:03:14", "scheduledStartTime": "2017-07-20T19:00:00", "tracks": [79], "races": ["2017-07-20_79_2"]}, {"id": "trio_2017-07-20_79_3", "status": "results", "startTime": "2017-07-20T19:28:38", "scheduledStartTime": "2017-07-20T19:25:00", "tracks": [79], "races": ["2017-07-20_79_3"]}, {"id": "trio_2017-07-20_79_4", "status": "results", "startTime": "2017-07-20T19:47:02", "scheduledStartTime": "2017-07-20T19:45:00", "tracks": [79], "races": ["2017-07-20_79_4"]}, {"id": "trio_2017-07-20_79_5", "status": "results", "startTime": "2017-07-20T20:11:54", "scheduledStartTime": "2017-07-20T20:10:00", "tracks": [79], "races": ["2017-07-20_79_5"]}, {"id": "trio_2017-07-20_79_6", "status": "results", "startTime": "2017-07-20T20:38:06", "scheduledStartTime": "2017-07-20T20:35:00", "tracks": [79], "races": ["2017-07-20_79_6"]}, {"id": "trio_2017-07-20_79_7", "status": "results", "startTime": "2017-07-20T21:06:34", "scheduledStartTime": "2017-07-20T21:00:00", "tracks": [79], "races": ["2017-07-20_79_7"]}, {"id": "trio_2017-07-20_79_8", "status": "results", "startTime": "2017-07-20T21:25:18", "scheduledStartTime": "2017-07-20T21:20:00", "tracks": [79], "races": ["2017-07-20_79_8"]}, {"id": "trio_2017-07-20_86_1", "status": "results", "startTime": "2017-07-20T18:31:20", "scheduledStartTime": "2017-07-20T18:30:00", "tracks": [86], "races": ["2017-07-20_86_1"]}, {"id": "trio_2017-07-20_86_2", "status": "results", "startTime": "2017-07-20T18:56:25", "scheduledStartTime": "2017-07-20T18:54:00", "tracks": [86], "races": ["2017-07-20_86_2"]}, {"id": "trio_2017-07-20_86_4", "status": "results", "startTime": "2017-07-20T19:45:51", "scheduledStartTime": "2017-07-20T19:42:00", "tracks": [86], "races": ["2017-07-20_86_4"]}, {"id": "trio_2017-07-20_86_5", "status": "results", "startTime": "2017-07-20T20:14:09", "scheduledStartTime": "2017-07-20T20:06:00", "tracks": [86], "races": ["2017-07-20_86_5"]}, {"id": "trio_2017-07-20_86_6", "status": "results", "startTime": "2017-07-20T20:40:09", "scheduledStartTime": "2017-07-20T20:30:00", "tracks": [86], "races": ["2017-07-20_86_6"]}, {"id": "trio_2017-07-20_86_7", "status": "results", "startTime": "2017-07-20T21:05:27", "scheduledStartTime": "2017-07-20T20:54:00", "tracks": [86], "races": ["2017-07-20_86_7"]}, {"id": "trio_2017-07-20_86_8", "status": "results", "startTime": "2017-07-20T21:30:11", "scheduledStartTime": "2017-07-20T21:16:00", "tracks": [86], "races": ["2017-07-20_86_8"]}, {"id": "trio_2017-07-20_86_9", "status": "results", "startTime": "2017-07-20T21:52:28", "scheduledStartTime": "2017-07-20T21:36:00", "tracks": [86], "races": ["2017-07-20_86_9"]}, {"id": "trio_2017-07-20_86_10", "status": "results", "startTime": "2017-07-20T22:21:23", "scheduledStartTime": "2017-07-20T21:56:00", "tracks": [86], "races": ["2017-07-20_86_10"]}, {"id": "trio_2017-07-20_89_1", "status": "results", "startTime": "2017-07-20T12:10:31", "scheduledStartTime": "2017-07-20T12:10:00", "tracks": [89], "races": ["2017-07-20_89_1"]}, {"id": "trio_2017-07-20_89_2", "status": "results", "startTime": "2017-07-20T12:45:49", "scheduledStartTime": "2017-07-20T12:45:00", "tracks": [89], "races": ["2017-07-20_89_2"]}, {"id": "trio_2017-07-20_89_3", "status": "results", "startTime": "2017-07-20T13:21:01", "scheduledStartTime": "2017-07-20T13:20:00", "tracks": [89], "races": ["2017-07-20_89_3"]}, {"id": "trio_2017-07-20_89_4", "status": "results", "startTime": "2017-07-20T13:55:46", "scheduledStartTime": "2017-07-20T13:55:00", "tracks": [89], "races": ["2017-07-20_89_4"]}, {"id": "trio_2017-07-20_89_5", "status": "results", "startTime": "2017-07-20T14:34:09", "scheduledStartTime": "2017-07-20T14:30:00", "tracks": [89], "races": ["2017-07-20_89_5"]}, {"id": "trio_2017-07-20_89_6", "status": "results", "startTime": "2017-07-20T15:06:18", "scheduledStartTime": "2017-07-20T15:05:00", "tracks": [89], "races": ["2017-07-20_89_6"]}, {"id": "trio_2017-07-20_89_7", "status": "results", "startTime": "2017-07-20T15:43:54", "scheduledStartTime": "2017-07-20T15:40:00", "tracks": [89], "races": ["2017-07-20_89_7"]}, {"id": "trio_2017-07-20_89_8", "status": "results", "startTime": "2017-07-20T16:20:56", "scheduledStartTime": "2017-07-20T16:15:00", "tracks": [89], "races": ["2017-07-20_89_8"]}, {"id": "trio_2017-07-20_89_9", "status": "results", "startTime": "2017-07-20T16:56:10", "scheduledStartTime": "2017-07-20T16:55:00", "tracks": [89], "races": ["2017-07-20_89_9"]}], "komb": [{"id": "komb_2017-07-20_79_1", "status": "results", "startTime": "2017-07-20T18:32:21", "scheduledStartTime": "2017-07-20T18:30:00", "tracks": [79], "races": ["2017-07-20_79_1"]}, {"id": "komb_2017-07-20_79_2", "status": "results", "startTime": "2017-07-20T19:03:14", "scheduledStartTime": "2017-07-20T19:00:00", "tracks": [79], "races": ["2017-07-20_79_2"]}, {"id": "komb_2017-07-20_79_3", "status": "results", "startTime": "2017-07-20T19:28:38", "scheduledStartTime": "2017-07-20T19:25:00", "tracks": [79], "races": ["2017-07-20_79_3"]}, {"id": "komb_2017-07-20_79_4", "status": "results", "startTime": "2017-07-20T19:47:02", "scheduledStartTime": "2017-07-20T19:45:00", "tracks": [79], "races": ["2017-07-20_79_4"]}, {"id": "komb_2017-07-20_79_5", "status": "results", "startTime": "2017-07-20T20:11:54", "scheduledStartTime": "2017-07-20T20:10:00", "tracks": [79], "races": ["2017-07-20_79_5"]}, {"id": "komb_2017-07-20_79_6", "status": "results", "startTime": "2017-07-20T20:38:06", "scheduledStartTime": "2017-07-20T20:35:00", "tracks": [79], "races": ["2017-07-20_79_6"]}, {"id": "komb_2017-07-20_79_7", "status": "results", "startTime": "2017-07-20T21:06:34", "scheduledStartTime": "2017-07-20T21:00:00", "tracks": [79], "races": ["2017-07-20_79_7"]}, {"id": "komb_2017-07-20_79_8", "status": "results", "startTime": "2017-07-20T21:25:18", "scheduledStartTime": "2017-07-20T21:20:00", "tracks": [79], "races": ["2017-07-20_79_8"]}, {"id": "komb_2017-07-20_89_1", "status": "results", "startTime": "2017-07-20T12:10:31", "scheduledStartTime": "2017-07-20T12:10:00", "tracks": [89], "races": ["2017-07-20_89_1"]}, {"id": "komb_2017-07-20_89_2", "status": "results", "startTime": "2017-07-20T12:45:49", "scheduledStartTime": "2017-07-20T12:45:00", "tracks": [89], "races": ["2017-07-20_89_2"]}, {"id": "komb_2017-07-20_89_3", "status": "results", "startTime": "2017-07-20T13:21:01", "scheduledStartTime": "2017-07-20T13:20:00", "tracks": [89], "races": ["2017-07-20_89_3"]}, {"id": "komb_2017-07-20_89_4", "status": "results", "startTime": "2017-07-20T13:55:46", "scheduledStartTime": "2017-07-20T13:55:00", "tracks": [89], "races": ["2017-07-20_89_4"]}, {"id": "komb_2017-07-20_89_5", "status": "results", "startTime": "2017-07-20T14:34:09", "scheduledStartTime": "2017-07-20T14:30:00", "tracks": [89], "races": ["2017-07-20_89_5"]}, {"id": "komb_2017-07-20_89_6", "status": "results", "startTime": "2017-07-20T15:06:18", "scheduledStartTime": "2017-07-20T15:05:00", "tracks": [89], "races": ["2017-07-20_89_6"]}, {"id": "komb_2017-07-20_89_7", "status": "results", "startTime": "2017-07-20T15:43:54", "scheduledStartTime": "2017-07-20T15:40:00", "tracks": [89], "races": ["2017-07-20_89_7"]}, {"id": "komb_2017-07-20_89_8", "status": "results", "startTime": "2017-07-20T16:20:56", "scheduledStartTime": "2017-07-20T16:15:00", "tracks": [89], "races": ["2017-07-20_89_8"]}, {"id": "komb_2017-07-20_89_9", "status": "results", "startTime": "2017-07-20T16:56:10", "scheduledStartTime": "2017-07-20T16:55:00", "tracks": [89], "races": ["2017-07-20_89_9"]}], "tvilling": [{"id": "tvilling_2017-07-20_9_1", "status": "results", "startTime": "2017-07-20T18:15:14", "scheduledStartTime": "2017-07-20T18:15:00", "tracks": [9], "races": ["2017-07-20_9_1"]}, {"id": "tvilling_2017-07-20_9_2", "status": "results", "startTime": "2017-07-20T18:37:36", "scheduledStartTime": "2017-07-20T18:37:00", "tracks": [9], "races": ["2017-07-20_9_2"]}, {"id": "tvilling_2017-07-20_9_3", "status": "results", "startTime": "2017-07-20T19:00:44", "scheduledStartTime": "2017-07-20T19:00:00", "tracks": [9], "races": ["2017-07-20_9_3"]}, {"id": "tvilling_2017-07-20_9_4", "status": "results", "startTime": "2017-07-20T19:25:07", "scheduledStartTime": "2017-07-20T19:25:00", "tracks": [9], "races": ["2017-07-20_9_4"]}, {"id": "tvilling_2017-07-20_9_5", "status": "results", "startTime": "2017-07-20T19:48:21", "scheduledStartTime": "2017-07-20T19:47:00", "tracks": [9], "races": ["2017-07-20_9_5"]}, {"id": "tvilling_2017-07-20_9_6", "status": "results", "startTime": "2017-07-20T20:09:12", "scheduledStartTime": "2017-07-20T20:09:00", "tracks": [9], "races": ["2017-07-20_9_6"]}, {"id": "tvilling_2017-07-20_9_7", "status": "results", "startTime": "2017-07-20T20:35:29", "scheduledStartTime": "2017-07-20T20:31:00", "tracks": [9], "races": ["2017-07-20_9_7"]}, {"id": "tvilling_2017-07-20_9_8", "status": "results", "startTime": "2017-07-20T20:54:49", "scheduledStartTime": "2017-07-20T20:53:00", "tracks": [9], "races": ["2017-07-20_9_8"]}, {"id": "tvilling_2017-07-20_9_9", "status": "results", "startTime": "2017-07-20T21:15:26", "scheduledStartTime": "2017-07-20T21:13:00", "tracks": [9], "races": ["2017-07-20_9_9"]}, {"id": "tvilling_2017-07-20_9_10", "status": "results", "startTime": "2017-07-20T21:35:34", "scheduledStartTime": "2017-07-20T21:31:00", "tracks": [9], "races": ["2017-07-20_9_10"]}, {"id": "tvilling_2017-07-20_9_11", "status": "results", "startTime": "2017-07-20T21:51:00", "scheduledStartTime": "2017-07-20T21:48:00", "tracks": [9], "races": ["2017-07-20_9_11"]}, {"id": "tvilling_2017-07-20_9_12", "status": "results", "startTime": "2017-07-20T22:07:02", "scheduledStartTime": "2017-07-20T22:04:00", "tracks": [9], "races": ["2017-07-20_9_12"]}, {"id": "tvilling_2017-07-20_32_1", "status": "results", "startTime": "2017-07-20T18:25:58", "scheduledStartTime": "2017-07-20T18:25:00", "tracks": [32], "races": ["2017-07-20_32_1"]}, {"id": "tvilling_2017-07-20_32_2", "status": "results", "startTime": "2017-07-20T18:48:20", "scheduledStartTime": "2017-07-20T18:48:00", "tracks": [32], "races": ["2017-07-20_32_2"]}, {"id": "tvilling_2017-07-20_32_3", "status": "results", "startTime": "2017-07-20T19:11:15", "scheduledStartTime": "2017-07-20T19:11:00", "tracks": [32], "races": ["2017-07-20_32_3"]}, {"id": "tvilling_2017-07-20_32_4", "status": "results", "startTime": "2017-07-20T19:39:20", "scheduledStartTime": "2017-07-20T19:35:00", "tracks": [32], "races": ["2017-07-20_32_4"]}, {"id": "tvilling_2017-07-20_32_5", "status": "results", "startTime": "2017-07-20T19:59:04", "scheduledStartTime": "2017-07-20T19:58:00", "tracks": [32], "races": ["2017-07-20_32_5"]}, {"id": "tvilling_2017-07-20_32_6", "status": "results", "startTime": "2017-07-20T20:20:35", "scheduledStartTime": "2017-07-20T20:20:00", "tracks": [32], "races": ["2017-07-20_32_6"]}, {"id": "tvilling_2017-07-20_32_7", "status": "results", "startTime": "2017-07-20T20:42:55", "scheduledStartTime": "2017-07-20T20:42:00", "tracks": [32], "races": ["2017-07-20_32_7"]}, {"id": "tvilling_2017-07-20_32_8", "status": "results", "startTime": "2017-07-20T21:06:29", "scheduledStartTime": "2017-07-20T21:03:00", "tracks": [32], "races": ["2017-07-20_32_8"]}, {"id": "tvilling_2017-07-20_32_9", "status": "results", "startTime": "2017-07-20T21:25:08", "scheduledStartTime": "2017-07-20T21:21:00", "tracks": [32], "races": ["2017-07-20_32_9"]}, {"id": "tvilling_2017-07-20_32_10", "status": "results", "startTime": "2017-07-20T21:45:12", "scheduledStartTime": "2017-07-20T21:38:00", "tracks": [32], "races": ["2017-07-20_32_10"]}, {"id": "tvilling_2017-07-20_44_1", "status": "results", "startTime": "2017-07-20T12:20:46", "scheduledStartTime": "2017-07-20T12:20:00", "tracks": [44], "races": ["2017-07-20_44_1"]}, {"id": "tvilling_2017-07-20_44_2", "status": "results", "startTime": "2017-07-20T12:40:24", "scheduledStartTime": "2017-07-20T12:40:00", "tracks": [44], "races": ["2017-07-20_44_2"]}, {"id": "tvilling_2017-07-20_44_3", "status": "results", "startTime": "2017-07-20T13:00:23", "scheduledStartTime": "2017-07-20T13:00:00", "tracks": [44], "races": ["2017-07-20_44_3"]}, {"id": "tvilling_2017-07-20_44_4", "status": "results", "startTime": "2017-07-20T13:20:23", "scheduledStartTime": "2017-07-20T13:20:00", "tracks": [44], "races": ["2017-07-20_44_4"]}, {"id": "tvilling_2017-07-20_44_5", "status": "results", "startTime": "2017-07-20T14:00:45", "scheduledStartTime": "2017-07-20T14:00:00", "tracks": [44], "races": ["2017-07-20_44_5"]}, {"id": "tvilling_2017-07-20_44_6", "status": "results", "startTime": "2017-07-20T14:20:22", "scheduledStartTime": "2017-07-20T14:20:00", "tracks": [44], "races": ["2017-07-20_44_6"]}, {"id": "tvilling_2017-07-20_44_7", "status": "results", "startTime": "2017-07-20T14:40:26", "scheduledStartTime": "2017-07-20T14:40:00", "tracks": [44], "races": ["2017-07-20_44_7"]}, {"id": "tvilling_2017-07-20_44_8", "status": "results", "startTime": "2017-07-20T15:00:55", "scheduledStartTime": "2017-07-20T15:00:00", "tracks": [44], "races": ["2017-07-20_44_8"]}, {"id": "tvilling_2017-07-20_44_9", "status": "results", "startTime": "2017-07-20T15:20:28", "scheduledStartTime": "2017-07-20T15:20:00", "tracks": [44], "races": ["2017-07-20_44_9"]}, {"id": "tvilling_2017-07-20_51_1", "status": "results", "startTime": "2017-07-20T09:33:07", "scheduledStartTime": "2017-07-20T09:32:00", "tracks": [51], "races": ["2017-07-20_51_1"]}, {"id": "tvilling_2017-07-20_51_2", "status": "results", "startTime": "2017-07-20T09:58:58", "scheduledStartTime": "2017-07-20T09:58:00", "tracks": [51], "races": ["2017-07-20_51_2"]}, {"id": "tvilling_2017-07-20_51_3", "status": "results", "startTime": "2017-07-20T10:33:08", "scheduledStartTime": "2017-07-20T10:32:00", "tracks": [51], "races": ["2017-07-20_51_3"]}, {"id": "tvilling_2017-07-20_51_4", "status": "results", "startTime": "2017-07-20T11:01:08", "scheduledStartTime": "2017-07-20T11:00:00", "tracks": [51], "races": ["2017-07-20_51_4"]}, {"id": "tvilling_2017-07-20_51_5", "status": "results", "startTime": "2017-07-20T11:31:10", "scheduledStartTime": "2017-07-20T11:30:00", "tracks": [51], "races": ["2017-07-20_51_5"]}, {"id": "tvilling_2017-07-20_51_6", "status": "results", "startTime": "2017-07-20T12:01:22", "scheduledStartTime": "2017-07-20T12:00:00", "tracks": [51], "races": ["2017-07-20_51_6"]}, {"id": "tvilling_2017-07-20_51_7", "status": "results", "startTime": "2017-07-20T12:31:00", "scheduledStartTime": "2017-07-20T12:30:00", "tracks": [51], "races": ["2017-07-20_51_7"]}, {"id": "tvilling_2017-07-20_51_8", "status": "results", "startTime": "2017-07-20T13:00:54", "scheduledStartTime": "2017-07-20T13:00:00", "tracks": [51], "races": ["2017-07-20_51_8"]}, {"id": "tvilling_2017-07-20_51_9", "status": "results", "startTime": "2017-07-20T13:31:30", "scheduledStartTime": "2017-07-20T13:30:00", "tracks": [51], "races": ["2017-07-20_51_9"]}, {"id": "tvilling_2017-07-20_51_10", "status": "results", "startTime": "2017-07-20T14:00:51", "scheduledStartTime": "2017-07-20T14:00:00", "tracks": [51], "races": ["2017-07-20_51_10"]}, {"id": "tvilling_2017-07-20_78_1", "status": "results", "startTime": "2017-07-20T13:40:46", "scheduledStartTime": "2017-07-20T13:40:00", "tracks": [78], "races": ["2017-07-20_78_1"]}, {"id": "tvilling_2017-07-20_78_2", "status": "results", "startTime": "2017-07-20T13:58:57", "scheduledStartTime": "2017-07-20T13:58:00", "tracks": [78], "races": ["2017-07-20_78_2"]}, {"id": "tvilling_2017-07-20_78_3", "status": "results", "startTime": "2017-07-20T14:10:45", "scheduledStartTime": "2017-07-20T14:10:00", "tracks": [78], "races": ["2017-07-20_78_3"]}, {"id": "tvilling_2017-07-20_78_4", "status": "results", "startTime": "2017-07-20T14:23:58", "scheduledStartTime": "2017-07-20T14:22:00", "tracks": [78], "races": ["2017-07-20_78_4"]}, {"id": "tvilling_2017-07-20_78_5", "status": "results", "startTime": "2017-07-20T14:35:42", "scheduledStartTime": "2017-07-20T14:34:00", "tracks": [78], "races": ["2017-07-20_78_5"]}], "vp": [{"id": "vp_2017-07-20_9_1", "status": "results", "startTime": "2017-07-20T18:15:14", "scheduledStartTime": "2017-07-20T18:15:00", "tracks": [9], "races": ["2017-07-20_9_1"]}, {"id": "vp_2017-07-20_9_2", "status": "results", "startTime": "2017-07-20T18:37:36", "scheduledStartTime": "2017-07-20T18:37:00", "tracks": [9], "races": ["2017-07-20_9_2"]}, {"id": "vp_2017-07-20_9_3", "status": "results", "startTime": "2017-07-20T19:00:44", "scheduledStartTime": "2017-07-20T19:00:00", "tracks": [9], "races": ["2017-07-20_9_3"]}, {"id": "vp_2017-07-20_9_4", "status": "results", "startTime": "2017-07-20T19:25:07", "scheduledStartTime": "2017-07-20T19:25:00", "tracks": [9], "races": ["2017-07-20_9_4"]}, {"id": "vp_2017-07-20_9_5", "status": "results", "startTime": "2017-07-20T19:48:21", "scheduledStartTime": "2017-07-20T19:47:00", "tracks": [9], "races": ["2017-07-20_9_5"]}, {"id": "vp_2017-07-20_9_6", "status": "results", "startTime": "2017-07-20T20:09:12", "scheduledStartTime": "2017-07-20T20:09:00", "tracks": [9], "races": ["2017-07-20_9_6"]}, {"id": "vp_2017-07-20_9_7", "status": "results", "startTime": "2017-07-20T20:35:29", "scheduledStartTime": "2017-07-20T20:31:00", "tracks": [9], "races": ["2017-07-20_9_7"]}, {"id": "vp_2017-07-20_9_8", "status": "results", "startTime": "2017-07-20T20:54:49", "scheduledStartTime": "2017-07-20T20:53:00", "tracks": [9], "races": ["2017-07-20_9_8"]}, {"id": "vp_2017-07-20_9_9", "status": "results", "startTime": "2017-07-20T21:15:26", "scheduledStartTime": "2017-07-20T21:13:00", "tracks": [9], "races": ["2017-07-20_9_9"]}, {"id": "vp_2017-07-20_9_10", "status": "results", "startTime": "2017-07-20T21:35:34", "scheduledStartTime": "2017-07-20T21:31:00", "tracks": [9], "races": ["2017-07-20_9_10"]}, {"id": "vp_2017-07-20_9_11", "status": "results", "startTime": "2017-07-20T21:51:00", "scheduledStartTime": "2017-07-20T21:48:00", "tracks": [9], "races": ["2017-07-20_9_11"]}, {"id": "vp_2017-07-20_9_12", "status": "results", "startTime": "2017-07-20T22:07:02", "scheduledStartTime": "2017-07-20T22:04:00", "tracks": [9], "races": ["2017-07-20_9_12"]}, {"id": "vp_2017-07-20_32_1", "status": "results", "startTime": "2017-07-20T18:25:58", "scheduledStartTime": "2017-07-20T18:25:00", "tracks": [32], "races": ["2017-07-20_32_1"]}, {"id": "vp_2017-07-20_32_2", "status": "results", "startTime": "2017-07-20T18:48:20", "scheduledStartTime": "2017-07-20T18:48:00", "tracks": [32], "races": ["2017-07-20_32_2"]}, {"id": "vp_2017-07-20_32_3", "status": "results", "startTime": "2017-07-20T19:11:15", "scheduledStartTime": "2017-07-20T19:11:00", "tracks": [32], "races": ["2017-07-20_32_3"]}, {"id": "vp_2017-07-20_32_4", "status": "results", "startTime": "2017-07-20T19:39:20", "scheduledStartTime": "2017-07-20T19:35:00", "tracks": [32], "races": ["2017-07-20_32_4"]}, {"id": "vp_2017-07-20_32_5", "status": "results", "startTime": "2017-07-20T19:59:04", "scheduledStartTime": "2017-07-20T19:58:00", "tracks": [32], "races": ["2017-07-20_32_5"]}, {"id": "vp_2017-07-20_32_6", "status": "results", "startTime": "2017-07-20T20:20:35", "scheduledStartTime": "2017-07-20T20:20:00", "tracks": [32], "races": ["2017-07-20_32_6"]}, {"id": "vp_2017-07-20_32_7", "status": "results", "startTime": "2017-07-20T20:42:55", "scheduledStartTime": "2017-07-20T20:42:00", "tracks": [32], "races": ["2017-07-20_32_7"]}, {"id": "vp_2017-07-20_32_8", "status": "results", "startTime": "2017-07-20T21:06:29", "scheduledStartTime": "2017-07-20T21:03:00", "tracks": [32], "races": ["2017-07-20_32_8"]}, {"id": "vp_2017-07-20_32_9", "status": "results", "startTime": "2017-07-20T21:25:08", "scheduledStartTime": "2017-07-20T21:21:00", "tracks": [32], "races": ["2017-07-20_32_9"]}, {"id": "vp_2017-07-20_32_10", "status": "results", "startTime": "2017-07-20T21:45:12", "scheduledStartTime": "2017-07-20T21:38:00", "tracks": [32], "races": ["2017-07-20_32_10"]}, {"id": "vp_2017-07-20_44_1", "status": "results", "startTime": "2017-07-20T12:20:46", "scheduledStartTime": "2017-07-20T12:20:00", "tracks": [44], "races": ["2017-07-20_44_1"]}, {"id": "vp_2017-07-20_44_2", "status": "results", "startTime": "2017-07-20T12:40:24", "scheduledStartTime": "2017-07-20T12:40:00", "tracks": [44], "races": ["2017-07-20_44_2"]}, {"id": "vp_2017-07-20_44_3", "status": "results", "startTime": "2017-07-20T13:00:23", "scheduledStartTime": "2017-07-20T13:00:00", "tracks": [44], "races": ["2017-07-20_44_3"]}, {"id": "vp_2017-07-20_44_4", "status": "results", "startTime": "2017-07-20T13:20:23", "scheduledStartTime": "2017-07-20T13:20:00", "tracks": [44], "races": ["2017-07-20_44_4"]}, {"id": "vp_2017-07-20_44_5", "status": "results", "startTime": "2017-07-20T14:00:45", "scheduledStartTime": "2017-07-20T14:00:00", "tracks": [44], "races": ["2017-07-20_44_5"]}, {"id": "vp_2017-07-20_44_6", "status": "results", "startTime": "2017-07-20T14:20:22", "scheduledStartTime": "2017-07-20T14:20:00", "tracks": [44], "races": ["2017-07-20_44_6"]}, {"id": "vp_2017-07-20_44_7", "status": "results", "startTime": "2017-07-20T14:40:26", "scheduledStartTime": "2017-07-20T14:40:00", "tracks": [44], "races": ["2017-07-20_44_7"]}, {"id": "vp_2017-07-20_44_8", "status": "results", "startTime": "2017-07-20T15:00:55", "scheduledStartTime": "2017-07-20T15:00:00", "tracks": [44], "races": ["2017-07-20_44_8"]}, {"id": "vp_2017-07-20_44_9", "status": "results", "startTime": "2017-07-20T15:20:28", "scheduledStartTime": "2017-07-20T15:20:00", "tracks": [44], "races": ["2017-07-20_44_9"]}, {"id": "vp_2017-07-20_51_1", "status": "results", "startTime": "2017-07-20T09:33:07", "scheduledStartTime": "2017-07-20T09:32:00", "tracks": [51], "races": ["2017-07-20_51_1"]}, {"id": "vp_2017-07-20_51_2", "status": "results", "startTime": "2017-07-20T09:58:58", "scheduledStartTime": "2017-07-20T09:58:00", "tracks": [51], "races": ["2017-07-20_51_2"]}, {"id": "vp_2017-07-20_51_3", "status": "results", "startTime": "2017-07-20T10:33:08", "scheduledStartTime": "2017-07-20T10:32:00", "tracks": [51], "races": ["2017-07-20_51_3"]}, {"id": "vp_2017-07-20_51_4", "status": "results", "startTime": "2017-07-20T11:01:08", "scheduledStartTime": "2017-07-20T11:00:00", "tracks": [51], "races": ["2017-07-20_51_4"]}, {"id": "vp_2017-07-20_51_5", "status": "results", "startTime": "2017-07-20T11:31:10", "scheduledStartTime": "2017-07-20T11:30:00", "tracks": [51], "races": ["2017-07-20_51_5"]}, {"id": "vp_2017-07-20_51_6", "status": "results", "startTime": "2017-07-20T12:01:22", "scheduledStartTime": "2017-07-20T12:00:00", "tracks": [51], "races": ["2017-07-20_51_6"]}, {"id": "vp_2017-07-20_51_7", "status": "results", "startTime": "2017-07-20T12:31:00", "scheduledStartTime": "2017-07-20T12:30:00", "tracks": [51], "races": ["2017-07-20_51_7"]}, {"id": "vp_2017-07-20_51_8", "status": "results", "startTime": "2017-07-20T13:00:54", "scheduledStartTime": "2017-07-20T13:00:00", "tracks": [51], "races": ["2017-07-20_51_8"]}, {"id": "vp_2017-07-20_51_9", "status": "results", "startTime": "2017-07-20T13:31:30", "scheduledStartTime": "2017-07-20T13:30:00", "tracks": [51], "races": ["2017-07-20_51_9"]}, {"id": "vp_2017-07-20_51_10", "status": "results", "startTime": "2017-07-20T14:00:51", "scheduledStartTime": "2017-07-20T14:00:00", "tracks": [51], "races": ["2017-07-20_51_10"]}, {"id": "vp_2017-07-20_78_1", "status": "results", "startTime": "2017-07-20T13:40:46", "scheduledStartTime": "2017-07-20T13:40:00", "tracks": [78], "races": ["2017-07-20_78_1"]}, {"id": "vp_2017-07-20_78_2", "status": "results", "startTime": "2017-07-20T13:58:57", "scheduledStartTime": "2017-07-20T13:58:00", "tracks": [78], "races": ["2017-07-20_78_2"]}, {"id": "vp_2017-07-20_78_3", "status": "results", "startTime": "2017-07-20T14:10:45", "scheduledStartTime": "2017-07-20T14:10:00", "tracks": [78], "races": ["2017-07-20_78_3"]}, {"id": "vp_2017-07-20_78_4", "status": "results", "startTime": "2017-07-20T14:23:58", "scheduledStartTime": "2017-07-20T14:22:00", "tracks": [78], "races": ["2017-07-20_78_4"]}, {"id": "vp_2017-07-20_78_5", "status": "results", "startTime": "2017-07-20T14:35:42", "scheduledStartTime": "2017-07-20T14:34:00", "tracks": [78], "races": ["2017-07-20_78_5"]}, {"id": "vp_2017-07-20_79_1", "status": "results", "startTime": "2017-07-20T18:32:21", "scheduledStartTime": "2017-07-20T18:30:00", "tracks": [79], "races": ["2017-07-20_79_1"]}, {"id": "vp_2017-07-20_79_2", "status": "results", "startTime": "2017-07-20T19:03:14", "scheduledStartTime": "2017-07-20T19:00:00", "tracks": [79], "races": ["2017-07-20_79_2"]}, {"id": "vp_2017-07-20_79_3", "status": "results", "startTime": "2017-07-20T19:28:38", "scheduledStartTime": "2017-07-20T19:25:00", "tracks": [79], "races": ["2017-07-20_79_3"]}, {"id": "vp_2017-07-20_79_4", "status": "results", "startTime": "2017-07-20T19:47:02", "scheduledStartTime": "2017-07-20T19:45:00", "tracks": [79], "races": ["2017-07-20_79_4"]}, {"id": "vp_2017-07-20_79_5", "status": "results", "startTime": "2017-07-20T20:11:54", "scheduledStartTime": "2017-07-20T20:10:00", "tracks": [79], "races": ["2017-07-20_79_5"]}, {"id": "vp_2017-07-20_79_6", "status": "results", "startTime": "2017-07-20T20:38:06", "scheduledStartTime": "2017-07-20T20:35:00", "tracks": [79], "races": ["2017-07-20_79_6"]}, {"id": "vp_2017-07-20_79_7", "status": "results", "startTime": "2017-07-20T21:06:34", "scheduledStartTime": "2017-07-20T21:00:00", "tracks": [79], "races": ["2017-07-20_79_7"]}, {"id": "vp_2017-07-20_79_8", "status": "results", "startTime": "2017-07-20T21:25:18", "scheduledStartTime": "2017-07-20T21:20:00", "tracks": [79], "races": ["2017-07-20_79_8"]}, {"id": "vp_2017-07-20_86_1", "status": "results", "startTime": "2017-07-20T18:31:20", "scheduledStartTime": "2017-07-20T18:30:00", "tracks": [86], "races": ["2017-07-20_86_1"]}, {"id": "vp_2017-07-20_86_2", "status": "results", "startTime": "2017-07-20T18:56:25", "scheduledStartTime": "2017-07-20T18:54:00", "tracks": [86], "races": ["2017-07-20_86_2"]}, {"id": "vp_2017-07-20_86_4", "status": "results", "startTime": "2017-07-20T19:45:51", "scheduledStartTime": "2017-07-20T19:42:00", "tracks": [86], "races": ["2017-07-20_86_4"]}, {"id": "vp_2017-07-20_86_5", "status": "results", "startTime": "2017-07-20T20:14:09", "scheduledStartTime": "2017-07-20T20:06:00", "tracks": [86], "races": ["2017-07-20_86_5"]}, {"id": "vp_2017-07-20_86_6", "status": "results", "startTime": "2017-07-20T20:40:09", "scheduledStartTime": "2017-07-20T20:30:00", "tracks": [86], "races": ["2017-07-20_86_6"]}, {"id": "vp_2017-07-20_86_7", "status": "results", "startTime": "2017-07-20T21:05:27", "scheduledStartTime": "2017-07-20T20:54:00", "tracks": [86], "races": ["2017-07-20_86_7"]}, {"id": "vp_2017-07-20_86_8", "status": "results", "startTime": "2017-07-20T21:30:11", "scheduledStartTime": "2017-07-20T21:16:00", "tracks": [86], "races": ["2017-07-20_86_8"]}, {"id": "vp_2017-07-20_86_9", "status": "results", "startTime": "2017-07-20T21:52:28", "scheduledStartTime": "2017-07-20T21:36:00", "tracks": [86], "races": ["2017-07-20_86_9"]}, {"id": "vp_2017-07-20_86_10", "status": "results", "startTime": "2017-07-20T22:21:23", "scheduledStartTime": "2017-07-20T21:56:00", "tracks": [86], "races": ["2017-07-20_86_10"]}, {"id": "vp_2017-07-20_89_1", "status": "results", "startTime": "2017-07-20T12:10:31", "scheduledStartTime": "2017-07-20T12:10:00", "tracks": [89], "races": ["2017-07-20_89_1"]}, {"id": "vp_2017-07-20_89_2", "status": "results", "startTime": "2017-07-20T12:45:49", "scheduledStartTime": "2017-07-20T12:45:00", "tracks": [89], "races": ["2017-07-20_89_2"]}, {"id": "vp_2017-07-20_89_3", "status": "results", "startTime": "2017-07-20T13:21:01", "scheduledStartTime": "2017-07-20T13:20:00", "tracks": [89], "races": ["2017-07-20_89_3"]}, {"id": "vp_2017-07-20_89_4", "status": "results", "startTime": "2017-07-20T13:55:46", "scheduledStartTime": "2017-07-20T13:55:00", "tracks": [89], "races": ["2017-07-20_89_4"]}, {"id": "vp_2017-07-20_89_5", "status": "results", "startTime": "2017-07-20T14:34:09", "scheduledStartTime": "2017-07-20T14:30:00", "tracks": [89], "races": ["2017-07-20_89_5"]}, {"id": "vp_2017-07-20_89_6", "status": "results", "startTime": "2017-07-20T15:06:18", "scheduledStartTime": "2017-07-20T15:05:00", "tracks": [89], "races": ["2017-07-20_89_6"]}, {"id": "vp_2017-07-20_89_8", "status": "results", "startTime": "2017-07-20T16:20:56", "scheduledStartTime": "2017-07-20T16:15:00", "tracks": [89], "races": ["2017-07-20_89_8"]}], "vinnare": [{"id": "vinnare_2017-07-20_9_1", "status": "results", "startTime": "2017-07-20T18:15:14", "scheduledStartTime": "2017-07-20T18:15:00", "tracks": [9], "races": ["2017-07-20_9_1"]}, {"id": "vinnare_2017-07-20_9_2", "status": "results", "startTime": "2017-07-20T18:37:36", "scheduledStartTime": "2017-07-20T18:37:00", "tracks": [9], "races": ["2017-07-20_9_2"]}, {"id": "vinnare_2017-07-20_9_3", "status": "results", "startTime": "2017-07-20T19:00:44", "scheduledStartTime": "2017-07-20T19:00:00", "tracks": [9], "races": ["2017-07-20_9_3"]}, {"id": "vinnare_2017-07-20_9_4", "status": "results", "startTime": "2017-07-20T19:25:07", "scheduledStartTime": "2017-07-20T19:25:00", "tracks": [9], "races": ["2017-07-20_9_4"]}, {"id": "vinnare_2017-07-20_9_5", "status": "results", "startTime": "2017-07-20T19:48:21", "scheduledStartTime": "2017-07-20T19:47:00", "tracks": [9], "races": ["2017-07-20_9_5"]}, {"id": "vinnare_2017-07-20_9_6", "status": "results", "startTime": "2017-07-20T20:09:12", "scheduledStartTime": "2017-07-20T20:09:00", "tracks": [9], "races": ["2017-07-20_9_6"]}, {"id": "vinnare_2017-07-20_9_7", "status": "results", "startTime": "2017-07-20T20:35:29", "scheduledStartTime": "2017-07-20T20:31:00", "tracks": [9], "races": ["2017-07-20_9_7"]}, {"id": "vinnare_2017-07-20_9_8", "status": "results", "startTime": "2017-07-20T20:54:49", "scheduledStartTime": "2017-07-20T20:53:00", "tracks": [9], "races": ["2017-07-20_9_8"]}, {"id": "vinnare_2017-07-20_9_9", "status": "results", "startTime": "2017-07-20T21:15:26", "scheduledStartTime": "2017-07-20T21:13:00", "tracks": [9], "races": ["2017-07-20_9_9"]}, {"id": "vinnare_2017-07-20_9_10", "status": "results", "startTime": "2017-07-20T21:35:34", "scheduledStartTime": "2017-07-20T21:31:00", "tracks": [9], "races": ["2017-07-20_9_10"]}, {"id": "vinnare_2017-07-20_9_11", "status": "results", "startTime": "2017-07-20T21:51:00", "scheduledStartTime": "2017-07-20T21:48:00", "tracks": [9], "races": ["2017-07-20_9_11"]}, {"id": "vinnare_2017-07-20_9_12", "status": "results", "startTime": "2017-07-20T22:07:02", "scheduledStartTime": "2017-07-20T22:04:00", "tracks": [9], "races": ["2017-07-20_9_12"]}, {"id": "vinnare_2017-07-20_32_1", "status": "results", "startTime": "2017-07-20T18:25:58", "scheduledStartTime": "2017-07-20T18:25:00", "tracks": [32], "races": ["2017-07-20_32_1"]}, {"id": "vinnare_2017-07-20_32_2", "status": "results", "startTime": "2017-07-20T18:48:20", "scheduledStartTime": "2017-07-20T18:48:00", "tracks": [32], "races": ["2017-07-20_32_2"]}, {"id": "vinnare_2017-07-20_32_3", "status": "results", "startTime": "2017-07-20T19:11:15", "scheduledStartTime": "2017-07-20T19:11:00", "tracks": [32], "races": ["2017-07-20_32_3"]}, {"id": "vinnare_2017-07-20_32_4", "status": "results", "startTime": "2017-07-20T19:39:20", "scheduledStartTime": "2017-07-20T19:35:00", "tracks": [32], "races": ["2017-07-20_32_4"]}, {"id": "vinnare_2017-07-20_32_5", "status": "results", "startTime": "2017-07-20T19:59:04", "scheduledStartTime": "2017-07-20T19:58:00", "tracks": [32], "races": ["2017-07-20_32_5"]}, {"id": "vinnare_2017-07-20_32_6", "status": "results", "startTime": "2017-07-20T20:20:35", "scheduledStartTime": "2017-07-20T20:20:00", "tracks": [32], "races": ["2017-07-20_32_6"]}, {"id": "vinnare_2017-07-20_32_7", "status": "results", "startTime": "2017-07-20T20:42:55", "scheduledStartTime": "2017-07-20T20:42:00", "tracks": [32], "races": ["2017-07-20_32_7"]}, {"id": "vinnare_2017-07-20_32_8", "status": "results", "startTime": "2017-07-20T21:06:29", "scheduledStartTime": "2017-07-20T21:03:00", "tracks": [32], "races": ["2017-07-20_32_8"]}, {"id": "vinnare_2017-07-20_32_9", "status": "results", "startTime": "2017-07-20T21:25:08", "scheduledStartTime": "2017-07-20T21:21:00", "tracks": [32], "races": ["2017-07-20_32_9"]}, {"id": "vinnare_2017-07-20_32_10", "status": "results", "startTime": "2017-07-20T21:45:12", "scheduledStartTime": "2017-07-20T21:38:00", "tracks": [32], "races": ["2017-07-20_32_10"]}, {"id": "vinnare_2017-07-20_44_1", "status": "results", "startTime": "2017-07-20T12:20:46", "scheduledStartTime": "2017-07-20T12:20:00", "tracks": [44], "races": ["2017-07-20_44_1"]}, {"id": "vinnare_2017-07-20_44_2", "status": "results", "startTime": "2017-07-20T12:40:24", "scheduledStartTime": "2017-07-20T12:40:00", "tracks": [44], "races": ["2017-07-20_44_2"]}, {"id": "vinnare_2017-07-20_44_3", "status": "results", "startTime": "2017-07-20T13:00:23", "scheduledStartTime": "2017-07-20T13:00:00", "tracks": [44], "races": ["2017-07-20_44_3"]}, {"id": "vinnare_2017-07-20_44_4", "status": "results", "startTime": "2017-07-20T13:20:23", "scheduledStartTime": "2017-07-20T13:20:00", "tracks": [44], "races": ["2017-07-20_44_4"]}, {"id": "vinnare_2017-07-20_44_5", "status": "results", "startTime": "2017-07-20T14:00:45", "scheduledStartTime": "2017-07-20T14:00:00", "tracks": [44], "races": ["2017-07-20_44_5"]}, {"id": "vinnare_2017-07-20_44_6", "status": "results", "startTime": "2017-07-20T14:20:22", "scheduledStartTime": "2017-07-20T14:20:00", "tracks": [44], "races": ["2017-07-20_44_6"]}, {"id": "vinnare_2017-07-20_44_7", "status": "results", "startTime": "2017-07-20T14:40:26", "scheduledStartTime": "2017-07-20T14:40:00", "tracks": [44], "races": ["2017-07-20_44_7"]}, {"id": "vinnare_2017-07-20_44_8", "status": "results", "startTime": "2017-07-20T15:00:55", "scheduledStartTime": "2017-07-20T15:00:00", "tracks": [44], "races": ["2017-07-20_44_8"]}, {"id": "vinnare_2017-07-20_44_9", "status": "results", "startTime": "2017-07-20T15:20:28", "scheduledStartTime": "2017-07-20T15:20:00", "tracks": [44], "races": ["2017-07-20_44_9"]}, {"id": "vinnare_2017-07-20_51_1", "status": "results", "startTime": "2017-07-20T09:33:07", "scheduledStartTime": "2017-07-20T09:32:00", "tracks": [51], "races": ["2017-07-20_51_1"]}, {"id": "vinnare_2017-07-20_51_2", "status": "results", "startTime": "2017-07-20T09:58:58", "scheduledStartTime": "2017-07-20T09:58:00", "tracks": [51], "races": ["2017-07-20_51_2"]}, {"id": "vinnare_2017-07-20_51_3", "status": "results", "startTime": "2017-07-20T10:33:08", "scheduledStartTime": "2017-07-20T10:32:00", "tracks": [51], "races": ["2017-07-20_51_3"]}, {"id": "vinnare_2017-07-20_51_4", "status": "results", "startTime": "2017-07-20T11:01:08", "scheduledStartTime": "2017-07-20T11:00:00", "tracks": [51], "races": ["2017-07-20_51_4"]}, {"id": "vinnare_2017-07-20_51_5", "status": "results", "startTime": "2017-07-20T11:31:10", "scheduledStartTime": "2017-07-20T11:30:00", "tracks": [51], "races": ["2017-07-20_51_5"]}, {"id": "vinnare_2017-07-20_51_6", "status": "results", "startTime": "2017-07-20T12:01:22", "scheduledStartTime": "2017-07-20T12:00:00", "tracks": [51], "races": ["2017-07-20_51_6"]}, {"id": "vinnare_2017-07-20_51_7", "status": "results", "startTime": "2017-07-20T12:31:00", "scheduledStartTime": "2017-07-20T12:30:00", "tracks": [51], "races": ["2017-07-20_51_7"]}, {"id": "vinnare_2017-07-20_51_8", "status": "results", "startTime": "2017-07-20T13:00:54", "scheduledStartTime": "2017-07-20T13:00:00", "tracks": [51], "races": ["2017-07-20_51_8"]}, {"id": "vinnare_2017-07-20_51_9", "status": "results", "startTime": "2017-07-20T13:31:30", "scheduledStartTime": "2017-07-20T13:30:00", "tracks": [51], "races": ["2017-07-20_51_9"]}, {"id": "vinnare_2017-07-20_51_10", "status": "results", "startTime": "2017-07-20T14:00:51", "scheduledStartTime": "2017-07-20T14:00:00", "tracks": [51], "races": ["2017-07-20_51_10"]}, {"id": "vinnare_2017-07-20_78_1", "status": "results", "startTime": "2017-07-20T13:40:46", "scheduledStartTime": "2017-07-20T13:40:00", "tracks": [78], "races": ["2017-07-20_78_1"]}, {"id": "vinnare_2017-07-20_78_2", "status": "results", "startTime": "2017-07-20T13:58:57", "scheduledStartTime": "2017-07-20T13:58:00", "tracks": [78], "races": ["2017-07-20_78_2"]}, {"id": "vinnare_2017-07-20_78_3", "status": "results", "startTime": "2017-07-20T14:10:45", "scheduledStartTime": "2017-07-20T14:10:00", "tracks": [78], "races": ["2017-07-20_78_3"]}, {"id": "vinnare_2017-07-20_78_4", "status": "results", "startTime": "2017-07-20T14:23:58", "scheduledStartTime": "2017-07-20T14:22:00", "tracks": [78], "races": ["2017-07-20_78_4"]}, {"id": "vinnare_2017-07-20_78_5", "status": "results", "startTime": "2017-07-20T14:35:42", "scheduledStartTime": "2017-07-20T14:34:00", "tracks": [78], "races": ["2017-07-20_78_5"]}, {"id": "vinnare_2017-07-20_79_1", "status": "results", "startTime": "2017-07-20T18:32:21", "scheduledStartTime": "2017-07-20T18:30:00", "tracks": [79], "races": ["2017-07-20_79_1"]}, {"id": "vinnare_2017-07-20_79_2", "status": "results", "startTime": "2017-07-20T19:03:14", "scheduledStartTime": "2017-07-20T19:00:00", "tracks": [79], "races": ["2017-07-20_79_2"]}, {"id": "vinnare_2017-07-20_79_3", "status": "results", "startTime": "2017-07-20T19:28:38", "scheduledStartTime": "2017-07-20T19:25:00", "tracks": [79], "races": ["2017-07-20_79_3"]}, {"id": "vinnare_2017-07-20_79_4", "status": "results", "startTime": "2017-07-20T19:47:02", "scheduledStartTime": "2017-07-20T19:45:00", "tracks": [79], "races": ["2017-07-20_79_4"]}, {"id": "vinnare_2017-07-20_79_5", "status": "results", "startTime": "2017-07-20T20:11:54", "scheduledStartTime": "2017-07-20T20:10:00", "tracks": [79], "races": ["2017-07-20_79_5"]}, {"id": "vinnare_2017-07-20_79_6", "status": "results", "startTime": "2017-07-20T20:38:06", "scheduledStartTime": "2017-07-20T20:35:00", "tracks": [79], "races": ["2017-07-20_79_6"]}, {"id": "vinnare_2017-07-20_79_7", "status": "results", "startTime": "2017-07-20T21:06:34", "scheduledStartTime": "2017-07-20T21:00:00", "tracks": [79], "races": ["2017-07-20_79_7"]}, {"id": "vinnare_2017-07-20_79_8", "status": "results", "startTime": "2017-07-20T21:25:18", "scheduledStartTime": "2017-07-20T21:20:00", "tracks": [79], "races": ["2017-07-20_79_8"]}, {"id": "vinnare_2017-07-20_86_1", "status": "results", "startTime": "2017-07-20T18:31:20", "scheduledStartTime": "2017-07-20T18:30:00", "tracks": [86], "races": ["2017-07-20_86_1"]}, {"id": "vinnare_2017-07-20_86_2", "status": "results", "startTime": "2017-07-20T18:56:25", "scheduledStartTime": "2017-07-20T18:54:00", "tracks": [86], "races": ["2017-07-20_86_2"]}, {"id": "vinnare_2017-07-20_86_3", "status": "results", "startTime": "2017-07-20T19:20:22", "scheduledStartTime": "2017-07-20T19:18:00", "tracks": [86], "races": ["2017-07-20_86_3"]}, {"id": "vinnare_2017-07-20_86_4", "status": "results", "startTime": "2017-07-20T19:45:51", "scheduledStartTime": "2017-07-20T19:42:00", "tracks": [86], "races": ["2017-07-20_86_4"]}, {"id": "vinnare_2017-07-20_86_5", "status": "results", "startTime": "2017-07-20T20:14:09", "scheduledStartTime": "2017-07-20T20:06:00", "tracks": [86], "races": ["2017-07-20_86_5"]}, {"id": "vinnare_2017-07-20_86_6", "status": "results", "startTime": "2017-07-20T20:40:09", "scheduledStartTime": "2017-07-20T20:30:00", "tracks": [86], "races": ["2017-07-20_86_6"]}, {"id": "vinnare_2017-07-20_86_7", "status": "results", "startTime": "2017-07-20T21:05:27", "scheduledStartTime": "2017-07-20T20:54:00", "tracks": [86], "races": ["2017-07-20_86_7"]}, {"id": "vinnare_2017-07-20_86_8", "status": "results", "startTime": "2017-07-20T21:30:11", "scheduledStartTime": "2017-07-20T21:16:00", "tracks": [86], "races": ["2017-07-20_86_8"]}, {"id": "vinnare_2017-07-20_86_9", "status": "results", "startTime": "2017-07-20T21:52:28", "scheduledStartTime": "2017-07-20T21:36:00", "tracks": [86], "races": ["2017-07-20_86_9"]}, {"id": "vinnare_2017-07-20_86_10", "status": "results", "startTime": "2017-07-20T22:21:23", "scheduledStartTime": "2017-07-20T21:56:00", "tracks": [86], "races": ["2017-07-20_86_10"]}, {"id": "vinnare_2017-07-20_89_1", "status": "results", "startTime": "2017-07-20T12:10:31", "scheduledStartTime": "2017-07-20T12:10:00", "tracks": [89], "races": ["2017-07-20_89_1"]}, {"id": "vinnare_2017-07-20_89_2", "status": "results", "startTime": "2017-07-20T12:45:49", "scheduledStartTime": "2017-07-20T12:45:00", "tracks": [89], "races": ["2017-07-20_89_2"]}, {"id": "vinnare_2017-07-20_89_3", "status": "results", "startTime": "2017-07-20T13:21:01", "scheduledStartTime": "2017-07-20T13:20:00", "tracks": [89], "races": ["2017-07-20_89_3"]}, {"id": "vinnare_2017-07-20_89_4", "status": "results", "startTime": "2017-07-20T13:55:46", "scheduledStartTime": "2017-07-20T13:55:00", "tracks": [89], "races": ["2017-07-20_89_4"]}, {"id": "vinnare_2017-07-20_89_5", "status": "results", "startTime": "2017-07-20T14:34:09", "scheduledStartTime": "2017-07-20T14:30:00", "tracks": [89], "races": ["2017-07-20_89_5"]}, {"id": "vinnare_2017-07-20_89_6", "status": "results", "startTime": "2017-07-20T15:06:18", "scheduledStartTime": "2017-07-20T15:05:00", "tracks": [89], "races": ["2017-07-20_89_6"]}, {"id": "vinnare_2017-07-20_89_7", "status": "results", "startTime": "2017-07-20T15:43:54", "scheduledStartTime": "2017-07-20T15:40:00", "tracks": [89], "races": ["2017-07-20_89_7"]}, {"id": "vinnare_2017-07-20_89_8", "status": "results", "startTime": "2017-07-20T16:20:56", "scheduledStartTime": "2017-07-20T16:15:00", "tracks": [89], "races": ["2017-07-20_89_8"]}, {"id": "vinnare_2017-07-20_89_9", "status": "results", "startTime": "2017-07-20T16:56:10", "scheduledStartTime": "2017-07-20T16:55:00", "tracks": [89], "races": ["2017-07-20_89_9"]}], "plats": [{"id": "plats_2017-07-20_9_1", "status": "results", "startTime": "2017-07-20T18:15:14", "scheduledStartTime": "2017-07-20T18:15:00", "tracks": [9], "races": ["2017-07-20_9_1"]}, {"id": "plats_2017-07-20_9_2", "status": "results", "startTime": "2017-07-20T18:37:36", "scheduledStartTime": "2017-07-20T18:37:00", "tracks": [9], "races": ["2017-07-20_9_2"]}, {"id": "plats_2017-07-20_9_3", "status": "results", "startTime": "2017-07-20T19:00:44", "scheduledStartTime": "2017-07-20T19:00:00", "tracks": [9], "races": ["2017-07-20_9_3"]}, {"id": "plats_2017-07-20_9_4", "status": "results", "startTime": "2017-07-20T19:25:07", "scheduledStartTime": "2017-07-20T19:25:00", "tracks": [9], "races": ["2017-07-20_9_4"]}, {"id": "plats_2017-07-20_9_5", "status": "results", "startTime": "2017-07-20T19:48:21", "scheduledStartTime": "2017-07-20T19:47:00", "tracks": [9], "races": ["2017-07-20_9_5"]}, {"id": "plats_2017-07-20_9_6", "status": "results", "startTime": "2017-07-20T20:09:12", "scheduledStartTime": "2017-07-20T20:09:00", "tracks": [9], "races": ["2017-07-20_9_6"]}, {"id": "plats_2017-07-20_9_7", "status": "results", "startTime": "2017-07-20T20:35:29", "scheduledStartTime": "2017-07-20T20:31:00", "tracks": [9], "races": ["2017-07-20_9_7"]}, {"id": "plats_2017-07-20_9_8", "status": "results", "startTime": "2017-07-20T20:54:49", "scheduledStartTime": "2017-07-20T20:53:00", "tracks": [9], "races": ["2017-07-20_9_8"]}, {"id": "plats_2017-07-20_9_9", "status": "results", "startTime": "2017-07-20T21:15:26", "scheduledStartTime": "2017-07-20T21:13:00", "tracks": [9], "races": ["2017-07-20_9_9"]}, {"id": "plats_2017-07-20_9_10", "status": "results", "startTime": "2017-07-20T21:35:34", "scheduledStartTime": "2017-07-20T21:31:00", "tracks": [9], "races": ["2017-07-20_9_10"]}, {"id": "plats_2017-07-20_9_11", "status": "results", "startTime": "2017-07-20T21:51:00", "scheduledStartTime": "2017-07-20T21:48:00", "tracks": [9], "races": ["2017-07-20_9_11"]}, {"id": "plats_2017-07-20_9_12", "status": "results", "startTime": "2017-07-20T22:07:02", "scheduledStartTime": "2017-07-20T22:04:00", "tracks": [9], "races": ["2017-07-20_9_12"]}, {"id": "plats_2017-07-20_32_1", "status": "results", "startTime": "2017-07-20T18:25:58", "scheduledStartTime": "2017-07-20T18:25:00", "tracks": [32], "races": ["2017-07-20_32_1"]}, {"id": "plats_2017-07-20_32_2", "status": "results", "startTime": "2017-07-20T18:48:20", "scheduledStartTime": "2017-07-20T18:48:00", "tracks": [32], "races": ["2017-07-20_32_2"]}, {"id": "plats_2017-07-20_32_3", "status": "results", "startTime": "2017-07-20T19:11:15", "scheduledStartTime": "2017-07-20T19:11:00", "tracks": [32], "races": ["2017-07-20_32_3"]}, {"id": "plats_2017-07-20_32_4", "status": "results", "startTime": "2017-07-20T19:39:20", "scheduledStartTime": "2017-07-20T19:35:00", "tracks": [32], "races": ["2017-07-20_32_4"]}, {"id": "plats_2017-07-20_32_5", "status": "results", "startTime": "2017-07-20T19:59:04", "scheduledStartTime": "2017-07-20T19:58:00", "tracks": [32], "races": ["2017-07-20_32_5"]}, {"id": "plats_2017-07-20_32_6", "status": "results", "startTime": "2017-07-20T20:20:35", "scheduledStartTime": "2017-07-20T20:20:00", "tracks": [32], "races": ["2017-07-20_32_6"]}, {"id": "plats_2017-07-20_32_7", "status": "results", "startTime": "2017-07-20T20:42:55", "scheduledStartTime": "2017-07-20T20:42:00", "tracks": [32], "races": ["2017-07-20_32_7"]}, {"id": "plats_2017-07-20_32_8", "status": "results", "startTime": "2017-07-20T21:06:29", "scheduledStartTime": "2017-07-20T21:03:00", "tracks": [32], "races": ["2017-07-20_32_8"]}, {"id": "plats_2017-07-20_32_9", "status": "results", "startTime": "2017-07-20T21:25:08", "scheduledStartTime": "2017-07-20T21:21:00", "tracks": [32], "races": ["2017-07-20_32_9"]}, {"id": "plats_2017-07-20_32_10", "status": "results", "startTime": "2017-07-20T21:45:12", "scheduledStartTime": "2017-07-20T21:38:00", "tracks": [32], "races": ["2017-07-20_32_10"]}, {"id": "plats_2017-07-20_44_1", "status": "results", "startTime": "2017-07-20T12:20:46", "scheduledStartTime": "2017-07-20T12:20:00", "tracks": [44], "races": ["2017-07-20_44_1"]}, {"id": "plats_2017-07-20_44_2", "status": "results", "startTime": "2017-07-20T12:40:24", "scheduledStartTime": "2017-07-20T12:40:00", "tracks": [44], "races": ["2017-07-20_44_2"]}, {"id": "plats_2017-07-20_44_3", "status": "results", "startTime": "2017-07-20T13:00:23", "scheduledStartTime": "2017-07-20T13:00:00", "tracks": [44], "races": ["2017-07-20_44_3"]}, {"id": "plats_2017-07-20_44_4", "status": "results", "startTime": "2017-07-20T13:20:23", "scheduledStartTime": "2017-07-20T13:20:00", "tracks": [44], "races": ["2017-07-20_44_4"]}, {"id": "plats_2017-07-20_44_5", "status": "results", "startTime": "2017-07-20T14:00:45", "scheduledStartTime": "2017-07-20T14:00:00", "tracks": [44], "races": ["2017-07-20_44_5"]}, {"id": "plats_2017-07-20_44_6", "status": "results", "startTime": "2017-07-20T14:20:22", "scheduledStartTime": "2017-07-20T14:20:00", "tracks": [44], "races": ["2017-07-20_44_6"]}, {"id": "plats_2017-07-20_44_7", "status": "results", "startTime": "2017-07-20T14:40:26", "scheduledStartTime": "2017-07-20T14:40:00", "tracks": [44], "races": ["2017-07-20_44_7"]}, {"id": "plats_2017-07-20_44_8", "status": "results", "startTime": "2017-07-20T15:00:55", "scheduledStartTime": "2017-07-20T15:00:00", "tracks": [44], "races": ["2017-07-20_44_8"]}, {"id": "plats_2017-07-20_44_9", "status": "results", "startTime": "2017-07-20T15:20:28", "scheduledStartTime": "2017-07-20T15:20:00", "tracks": [44], "races": ["2017-07-20_44_9"]}, {"id": "plats_2017-07-20_51_1", "status": "results", "startTime": "2017-07-20T09:33:07", "scheduledStartTime": "2017-07-20T09:32:00", "tracks": [51], "races": ["2017-07-20_51_1"]}, {"id": "plats_2017-07-20_51_2", "status": "results", "startTime": "2017-07-20T09:58:58", "scheduledStartTime": "2017-07-20T09:58:00", "tracks": [51], "races": ["2017-07-20_51_2"]}, {"id": "plats_2017-07-20_51_3", "status": "results", "startTime": "2017-07-20T10:33:08", "scheduledStartTime": "2017-07-20T10:32:00", "tracks": [51], "races": ["2017-07-20_51_3"]}, {"id": "plats_2017-07-20_51_4", "status": "results", "startTime": "2017-07-20T11:01:08", "scheduledStartTime": "2017-07-20T11:00:00", "tracks": [51], "races": ["2017-07-20_51_4"]}, {"id": "plats_2017-07-20_51_5", "status": "results", "startTime": "2017-07-20T11:31:10", "scheduledStartTime": "2017-07-20T11:30:00", "tracks": [51], "races": ["2017-07-20_51_5"]}, {"id": "plats_2017-07-20_51_6", "status": "results", "startTime": "2017-07-20T12:01:22", "scheduledStartTime": "2017-07-20T12:00:00", "tracks": [51], "races": ["2017-07-20_51_6"]}, {"id": "plats_2017-07-20_51_7", "status": "results", "startTime": "2017-07-20T12:31:00", "scheduledStartTime": "2017-07-20T12:30:00", "tracks": [51], "races": ["2017-07-20_51_7"]}, {"id": "plats_2017-07-20_51_8", "status": "results", "startTime": "2017-07-20T13:00:54", "scheduledStartTime": "2017-07-20T13:00:00", "tracks": [51], "races": ["2017-07-20_51_8"]}, {"id": "plats_2017-07-20_51_9", "status": "results", "startTime": "2017-07-20T13:31:30", "scheduledStartTime": "2017-07-20T13:30:00", "tracks": [51], "races": ["2017-07-20_51_9"]}, {"id": "plats_2017-07-20_51_10", "status": "results", "startTime": "2017-07-20T14:00:51", "scheduledStartTime": "2017-07-20T14:00:00", "tracks": [51], "races": ["2017-07-20_51_10"]}, {"id": "plats_2017-07-20_78_1", "status": "results", "startTime": "2017-07-20T13:40:46", "scheduledStartTime": "2017-07-20T13:40:00", "tracks": [78], "races": ["2017-07-20_78_1"]}, {"id": "plats_2017-07-20_78_2", "status": "results", "startTime": "2017-07-20T13:58:57", "scheduledStartTime": "2017-07-20T13:58:00", "tracks": [78], "races": ["2017-07-20_78_2"]}, {"id": "plats_2017-07-20_78_3", "status": "results", "startTime": "2017-07-20T14:10:45", "scheduledStartTime": "2017-07-20T14:10:00", "tracks": [78], "races": ["2017-07-20_78_3"]}, {"id": "plats_2017-07-20_78_4", "status": "results", "startTime": "2017-07-20T14:23:58", "scheduledStartTime": "2017-07-20T14:22:00", "tracks": [78], "races": ["2017-07-20_78_4"]}, {"id": "plats_2017-07-20_78_5", "status": "results", "startTime": "2017-07-20T14:35:42", "scheduledStartTime": "2017-07-20T14:34:00", "tracks": [78], "races": ["2017-07-20_78_5"]}, {"id": "plats_2017-07-20_79_1", "status": "results", "startTime": "2017-07-20T18:32:21", "scheduledStartTime": "2017-07-20T18:30:00", "tracks": [79], "races": ["2017-07-20_79_1"]}, {"id": "plats_2017-07-20_79_2", "status": "results", "startTime": "2017-07-20T19:03:14", "scheduledStartTime": "2017-07-20T19:00:00", "tracks": [79], "races": ["2017-07-20_79_2"]}, {"id": "plats_2017-07-20_79_3", "status": "results", "startTime": "2017-07-20T19:28:38", "scheduledStartTime": "2017-07-20T19:25:00", "tracks": [79], "races": ["2017-07-20_79_3"]}, {"id": "plats_2017-07-20_79_4", "status": "results", "startTime": "2017-07-20T19:47:02", "scheduledStartTime": "2017-07-20T19:45:00", "tracks": [79], "races": ["2017-07-20_79_4"]}, {"id": "plats_2017-07-20_79_5", "status": "results", "startTime": "2017-07-20T20:11:54", "scheduledStartTime": "2017-07-20T20:10:00", "tracks": [79], "races": ["2017-07-20_79_5"]}, {"id": "plats_2017-07-20_79_6", "status": "results", "startTime": "2017-07-20T20:38:06", "scheduledStartTime": "2017-07-20T20:35:00", "tracks": [79], "races": ["2017-07-20_79_6"]}, {"id": "plats_2017-07-20_79_7", "status": "results", "startTime": "2017-07-20T21:06:34", "scheduledStartTime": "2017-07-20T21:00:00", "tracks": [79], "races": ["2017-07-20_79_7"]}, {"id": "plats_2017-07-20_79_8", "status": "results", "startTime": "2017-07-20T21:25:18", "scheduledStartTime": "2017-07-20T21:20:00", "tracks": [79], "races": ["2017-07-20_79_8"]}, {"id": "plats_2017-07-20_86_1", "status": "results", "startTime": "2017-07-20T18:31:20", "scheduledStartTime": "2017-07-20T18:30:00", "tracks": [86], "races": ["2017-07-20_86_1"]}, {"id": "plats_2017-07-20_86_2", "status": "results", "startTime": "2017-07-20T18:56:25", "scheduledStartTime": "2017-07-20T18:54:00", "tracks": [86], "races": ["2017-07-20_86_2"]}, {"id": "plats_2017-07-20_86_4", "status": "results", "startTime": "2017-07-20T19:45:51", "scheduledStartTime": "2017-07-20T19:42:00", "tracks": [86], "races": ["2017-07-20_86_4"]}, {"id": "plats_2017-07-20_86_5", "status": "results", "startTime": "2017-07-20T20:14:09", "scheduledStartTime": "2017-07-20T20:06:00", "tracks": [86], "races": ["2017-07-20_86_5"]}, {"id": "plats_2017-07-20_86_6", "status": "results", "startTime": "2017-07-20T20:40:09", "scheduledStartTime": "2017-07-20T20:30:00", "tracks": [86], "races": ["2017-07-20_86_6"]}, {"id": "plats_2017-07-20_86_7", "status": "results", "startTime": "2017-07-20T21:05:27", "scheduledStartTime": "2017-07-20T20:54:00", "tracks": [86], "races": ["2017-07-20_86_7"]}, {"id": "plats_2017-07-20_86_8", "status": "results", "startTime": "2017-07-20T21:30:11", "scheduledStartTime": "2017-07-20T21:16:00", "tracks": [86], "races": ["2017-07-20_86_8"]}, {"id": "plats_2017-07-20_86_9", "status": "results", "startTime": "2017-07-20T21:52:28", "scheduledStartTime": "2017-07-20T21:36:00", "tracks": [86], "races": ["2017-07-20_86_9"]}, {"id": "plats_2017-07-20_86_10", "status": "results", "startTime": "2017-07-20T22:21:23", "scheduledStartTime": "2017-07-20T21:56:00", "tracks": [86], "races": ["2017-07-20_86_10"]}, {"id": "plats_2017-07-20_89_1", "status": "results", "startTime": "2017-07-20T12:10:31", "scheduledStartTime": "2017-07-20T12:10:00", "tracks": [89], "races": ["2017-07-20_89_1"]}, {"id": "plats_2017-07-20_89_2", "status": "results", "startTime": "2017-07-20T12:45:49", "scheduledStartTime": "2017-07-20T12:45:00", "tracks": [89], "races": ["2017-07-20_89_2"]}, {"id": "plats_2017-07-20_89_3", "status": "results", "startTime": "2017-07-20T13:21:01", "scheduledStartTime": "2017-07-20T13:20:00", "tracks": [89], "races": ["2017-07-20_89_3"]}, {"id": "plats_2017-07-20_89_4", "status": "results", "startTime": "2017-07-20T13:55:46", "scheduledStartTime": "2017-07-20T13:55:00", "tracks": [89], "races": ["2017-07-20_89_4"]}, {"id": "plats_2017-07-20_89_5", "status": "results", "startTime": "2017-07-20T14:34:09", "scheduledStartTime": "2017-07-20T14:30:00", "tracks": [89], "races": ["2017-07-20_89_5"]}, {"id": "plats_2017-07-20_89_6", "status": "results", "startTime": "2017-07-20T15:06:18", "scheduledStartTime": "2017-07-20T15:05:00", "tracks": [89], "races": ["2017-07-20_89_6"]}, {"id": "plats_2017-07-20_89_8", "status": "results", "startTime": "2017-07-20T16:20:56", "scheduledStartTime": "2017-07-20T16:15:00", "tracks": [89], "races": ["2017-07-20_89_8"]}], "raket": [{"id": "raket_2017-07-20_9_1", "status": "results", "startTime": "2017-07-20T18:15:14", "scheduledStartTime": "2017-07-20T18:15:00", "tracks": [9], "races": ["2017-07-20_9_1", "2017-07-20_9_2", "2017-07-20_9_3", "2017-07-20_9_4", "2017-07-20_9_5", "2017-07-20_9_6", "2017-07-20_9_7", "2017-07-20_9_8", "2017-07-20_9_9", "2017-07-20_9_10", "2017-07-20_9_11", "2017-07-20_9_12"]}, {"id": "raket_2017-07-20_32_1", "status": "results", "startTime": "2017-07-20T18:25:58", "scheduledStartTime": "2017-07-20T18:25:00", "tracks": [32], "races": ["2017-07-20_32_1", "2017-07-20_32_2", "2017-07-20_32_3", "2017-07-20_32_4", "2017-07-20_32_5", "2017-07-20_32_6", "2017-07-20_32_7", "2017-07-20_32_8", "2017-07-20_32_9", "2017-07-20_32_10"]}, {"id": "raket_2017-07-20_44_1", "status": "results", "startTime": "2017-07-20T12:20:46", "scheduledStartTime": "2017-07-20T12:20:00", "tracks": [44], "races": ["2017-07-20_44_1", "2017-07-20_44_2", "2017-07-20_44_3", "2017-07-20_44_4", "2017-07-20_44_5", "2017-07-20_44_6", "2017-07-20_44_7", "2017-07-20_44_8", "2017-07-20_44_9"]}]}, "currentVersion": 1516648824473}